Workbook

Sheet Elenco Completo (Hub)
A1: FC ANDORRA (LaLiga Hypermotion) — CENTRAL DE ELENCO (DERIVADA DOS LOGS POR PARTIDA)
A2: Treinador: Carles Manso Rubio | Data: 19/10/2025 | 13J: 9V 4E 0D · 32 GP / 8 GC (Invicto!) | Gols Conciliados: 32 = 32 GP
A4: ID Atleta | B4: Nº Camisa | C4: Jogador | D4: Nome Completo | E4: Hierarquia Escalação (Treinador) | F4: Utilização Real (Derivada) | G4: Papel Contratual | H4: Posição Principal | I4: Posições Secundárias | J4: Setor | K4: Overall (OVR) | L4: Potencial (POT) | M4: Margem de Potencial (POT-OVR) | N4: Evolução Real no Save | O4: Idade | P4: Nascimento | Q4: Nacionalidade | R4: Valor de Mercado (€) | S4: Salário Semanal (€) | T4: Situação Multa Rescisória | U4: Fim Contrato | V4: Alerta Contratual | W4: Jogos (Logs) | X4: Titular (Logs) | Y4: Reserva (Logs) | Z4: Minutos (Logs) | AA4: % Minutos | AB4: Gols (Conciliado Logs) | AC4: Assistências (Bloco stndgs) | AD4: Participações (G+A) | AE4: G+A por 90m | AF4: Gols (Liga) | AG4: Assist. (Liga) | AH4: Gols (Pré-Temp/Copa) | AI4: Assist. (Pré-Temp/Copa) | AJ4: Clean Sheets | AK4: Nota Média (Logs) | AL4: Forma Recente | AM4: Confiança da Amostra | AN4: Recomendação Consultiva (Camada 3) | AO4: Justificativa Numérica | AP4: Descrição Derivada Automática
A5: 262498 | B5: 2 | C5: Álex Petxa | D5: Álex Petxarroman Eizaguirre | E5: Titular (LE) | F5: Titular Efetivo (49% min) | G5: Rodízio | H5: LD | I5: MC | J5: Defesa | K5: 66 | L5: 66 | M5: =L5-K5 -> 0 | N5: =K5-66 -> 0 | O5: 28 | P5: 07/02/1997 | Q5: Espanha | R5: 925000 | S5: 3600 | T5: Sem multa rescisória | U5: 2028 | V5: Seguro (até 2028) | W5: =COUNTIFS('Desempenho por Jogo (Logs)'!$G$5:$G$206, A5) -> 12 | X5: =COUNTIFS('Desempenho por Jogo (Logs)'!$G$5:$G$206, A5, 'Desempenho por Jogo (Logs)'!$J$5:$J$206, "<>RES") -> 7 | Y5: =COUNTIFS('Desempenho por Jogo (Logs)'!$G$5:$G$206, A5, 'Desempenho por Jogo (Logs)'!$J$5:$J$206, "RES") -> 5 | Z5: =SUMIFS('Desempenho por Jogo (Logs)'!$K$5:$K$206, 'Desempenho por Jogo (Logs)'!$G$5:$G$206, A5) -> 574 | AA5: =IF(Z5>0, Z5/540, 0) -> 0.491 | AB5: =SUMIFS('Desempenho por Jogo (Logs)'!$L$5:$L$206, 'Desempenho por Jogo (Logs)'!$G$5:$G$206, A5) -> 0 | AC5: 2 | AD5: =AB5+AC5 -> 2 | AE5: =IF(Z5>0, ROUND((AD5/Z5)*90, 2), 0) -> 0.31 | AF5: =SUMIFS('Desempenho por Jogo (Logs)'!$L$5:$L$206, 'Desempenho por Jogo (Logs)'!$G$5:$G$206, A5, 'Desempenho por Jogo (Logs)'!$C$5:$C$206, "*Liga*") -> 0 | AG5: 2 | AH5: =SUMIFS('Desempenho por Jogo (Logs)'!$L$5:$L$206, 'Desempenho por Jogo (Logs)'!$G$5:$G$206, A5, 'Desempenho por Jogo (Logs)'!$C$5:$C$206, "*Trophy*") -> 0 | AI5: 0 | AJ5: 0 | AK5: =IFERROR(ROUND(AVERAGEIFS('Desempenho por Jogo (Logs)'!$N$5:$N$206, 'Desempenho por Jogo (Logs)'!$G$5:$G$206, A5, 'Desempenho por Jogo (Logs)'!$N$5:$N$206, ">0"), 2), "S/N") -> 7.12 | AL5: Regular (6,72) | AM5: =IF(W5=0, "Nula (0 jogos)", IF(OR(W5<=2, Z5<150), "Baixa — Amostra Insuficiente", IF(AND(W5>=4, Z5>=240), "Alta", "Moderada"))) -> Alta (≥4J e ≥270m) | AN5: =IF(W5=0, "Sem minutagem no save", IF(OR(W5<=2, Z5<150), "Amostra insuficiente (" & W5 & "J / " & Z5 & "m) — Continuar observando", IF(AK5>=7.5, "Promover minutos / Titularidade em ascensão", IF(AK5>=7.0, "Manter minutagem atual", "Avaliar opções / Rotação")))) -> Titular Regular na Temporada — Manter | AO5: Titular com 574 min em 12J (49,1% do tempo possível, Nota 7,12) | AP5: Atleta de 28 anos (Espanha). posição LD (MC). hierarquia atual 'Titular (LE)'. Overall 66 e Potencial 66 (margem de potencial +0; evolução real no save +0). Soma 574 min em 12 partidas (7T/5R). com 0 gol(s) verificado(s) por partida. 2 assistência(s) na temporada (2 G+A) e nota média 7.12. Vínculo: contrato até 2028 (Rodízio). avaliado em € 925.000.
A6: 273022 | B6: 3 | C6: Yeray Cabanzón | D6: Yeray Cabanzón | E6: Titular (PD) | F6: Titular Efetivo (40% min) | G6: Rodízio | H6: MD | I6: PD | J6: Meio-Campo | K6: 67 | L6: 75 | M6: =L6-K6 -> 8 | N6: =K6-66 -> 1 | O6: 22 | P6: 15/05/2003 | Q6: Espanha | R6: 2300000 | S6: 3200 | T6: Sem multa rescisória | U6: 2027 | V6: Atenção: Expira em 2027 (2 anos) | W6: =COUNTIFS('Desempenho por Jogo (Logs)'!$G$5:$G$206, A6) -> 7 | X6: =COUNTIFS('Desempenho por Jogo (Logs)'!$G$5:$G$206, A6, 'Desempenho por Jogo (Logs)'!$J$5:$J$206, "<>RES") -> 6 | Y6: =COUNTIFS('Desempenho por Jogo (Logs)'!$G$5:$G$206, A6, 'Desempenho por Jogo (Logs)'!$J$5:$J$206, "RES") -> 1 | Z6: =SUMIFS('Desempenho por Jogo (Logs)'!$K$5:$K$206, 'Desempenho por Jogo (Logs)'!$G$5:$G$206, A6) -> 463 | AA6: =IF(Z6>0, Z6/540, 0) -> 0.396 | AB6: =SUMIFS('Desempenho por Jogo (Logs)'!$L$5:$L$206, 'Desempenho por Jogo (Logs)'!$G$5:$G$206, A6) -> 3 | AC6: 4 | AD6: =AB6+AC6 -> 7 | AE6: =IF(Z6>0, ROUND((AD6/Z6)*90, 2), 0) -> 1.36 | AF6: =SUMIFS('Desempenho por Jogo (Logs)'!$L$5:$L$206, 'Desempenho por Jogo (Logs)'!$G$5:$G$206, A6, 'Desempenho por Jogo (Logs)'!$C$5:$C$206, "*Liga*") -> 2 | AG6: 4 | AH6: =SUMIFS('Desempenho por Jogo (Logs)'!$L$5:$L$206, 'Desempenho por Jogo (Logs)'!$G$5:$G$206, A6, 'Desempenho por Jogo (Logs)'!$C$5:$C$206, "*Trophy*") -> 1 | AI6: 0 | AJ6: 0 | AK6: =IFERROR(ROUND(AVERAGEIFS('Desempenho por Jogo (Logs)'!$N$5:$N$206, 'Desempenho por Jogo (Logs)'!$G$5:$G$206, A6, 'Desempenho por Jogo (Logs)'!$N$5:$N$206, ">0"), 2), "S/N") -> 7.66 | AL6: Excelente (7,80) | AM6: =IF(W6=0, "Nula (0 jogos)", IF(OR(W6<=2, Z6<150), "Baixa — Amostra Insuficiente", IF(AND(W6>=4, Z6>=240), "Alta", "Moderada"))) -> Alta (≥4J e ≥270m) | AN6: =IF(W6=0, "Sem minutagem no save", IF(OR(W6<=2, Z6<150), "Amostra insuficiente (" & W6 & "J / " & Z6 & "m) — Continuar observando", IF(AK6>=7.5, "Promover minutos / Titularidade em ascensão", IF(AK6>=7.0, "Manter minutagem atual", "Avaliar opções / Rotação")))) -> Titular Regular na Temporada — Manter | AO6: Titular com 463 min em 7J (39,6% do tempo possível, Nota 7,66) | AP6: Atleta de 22 anos (Espanha). posição MD (PD). hierarquia atual 'Titular (PD)'. Overall 67 e Potencial 75 (margem de potencial +8; evolução real no save +1). Soma 463 min em 7 partidas (6T/1R). com 3 gol(s) verificado(s) por partida. 4 assistência(s) na temporada (7 G+A) e nota média 7.66. Vínculo: contrato até 2027 (Rodízio). avaliado em € 2.300.000.
A7: 271955 | B7: 5 | C7: Bomba | D7: Marc Bombardó Poyato | E7: Titular (ZAG) | F7: Titular Efetivo (65% min) | G7: Rodízio | H7: ZAG | I7: — | J7: Defesa | K7: 67 | L7: 78 | M7: =L7-K7 -> 11 | N7: =K7-65 -> 2 | O7: 19 | P7: 24/11/2005 | Q7: Espanha | R7: 1900000 | S7: 2000 | T7: € 4.150.000 | U7: 2027 | V7: Atenção: Expira em 2027 (2 anos) | W7: =COUNTIFS('Desempenho por Jogo (Logs)'!$G$5:$G$206, A7) -> 9 | X7: =COUNTIFS('Desempenho por Jogo (Logs)'!$G$5:$G$206, A7, 'Desempenho por Jogo (Logs)'!$J$5:$J$206, "<>RES") -> 9 | Y7: =COUNTIFS('Desempenho por Jogo (Logs)'!$G$5:$G$206, A7, 'Desempenho por Jogo (Logs)'!$J$5:$J$206, "RES") -> 0 | Z7: =SUMIFS('Desempenho por Jogo (Logs)'!$K$5:$K$206, 'Desempenho por Jogo (Logs)'!$G$5:$G$206, A7) -> 765 | AA7: =IF(Z7>0, Z7/540, 0) -> 0.654 | AB7: =SUMIFS('Desempenho por Jogo (Logs)'!$L$5:$L$206, 'Desempenho por Jogo (Logs)'!$G$5:$G$206, A7) -> 0 | AC7: 0 | AD7: =AB7+AC7 -> 0 | AE7: =IF(Z7>0, ROUND((AD7/Z7)*90, 2), 0) -> 0 | AF7: =SUMIFS('Desempenho por Jogo (Logs)'!$L$5:$L$206, 'Desempenho por Jogo (Logs)'!$G$5:$G$206, A7, 'Desempenho por Jogo (Logs)'!$C$5:$C$206, "*Liga*") -> 0 | AG7: 0 | AH7: =SUMIFS('Desempenho por Jogo (Logs)'!$L$5:$L$206, 'Desempenho por Jogo (Logs)'!$G$5:$G$206, A7, 'Desempenho por Jogo (Logs)'!$C$5:$C$206, "*Trophy*") -> 0 | AI7: 0 | AJ7: 0 | AK7: =IFERROR(ROUND(AVERAGEIFS('Desempenho por Jogo (Logs)'!$N$5:$N$206, 'Desempenho por Jogo (Logs)'!$G$5:$G$206, A7, 'Desempenho por Jogo (Logs)'!$N$5:$N$206, ">0"), 2), "S/N") -> 7.04 | AL7: Boa (7,04) | AM7: =IF(W7=0, "Nula (0 jogos)", IF(OR(W7<=2, Z7<150), "Baixa — Amostra Insuficiente", IF(AND(W7>=4, Z7>=240), "Alta", "Moderada"))) -> Alta (≥4J e ≥270m) | AN7: =IF(W7=0, "Sem minutagem no save", IF(OR(W7<=2, Z7<150), "Amostra insuficiente (" & W7 & "J / " & Z7 & "m) — Continuar observando", IF(AK7>=7.5, "Promover minutos / Titularidade em ascensão", IF(AK7>=7.0, "Manter minutagem atual", "Avaliar opções / Rotação")))) -> Jovem em Desenvolvimento Ativo — Manter Minutagem | AO7: 19 anos, POT 78 (+11 margem) e 765 min disputados (9J) | AP7: Atleta de 19 anos (Espanha). posição ZAG. hierarquia atual 'Titular (ZAG)'. Overall 67 e Potencial 78 (margem de potencial +11; evolução real no save +2). Soma 765 min em 9 partidas (9T/0R). com 0 gol(s) verificado(s) por partida. 0 assistência(s) na temporada (0 G+A) e nota média 7.04. Vínculo: contrato até 2027 (Rodízio). avaliado em € 1.900.000.
A8: 266100 | B8: 6 | C8: Daniel Villahermosa | D8: Daniel Villahermosa | E8: Titular (MC) | F8: Titular Efetivo (60% min) | G8: Rodízio | H8: MC | I8: VOL | J8: Meio-Campo | K8: 68 | L8: 70 | M8: =L8-K8 -> 2 | N8: =K8-67 -> 1 | O8: 24 | P8: 03/01/2001 | Q8: Espanha | R8: 1600000 | S8: 3700 | T8: € 2.600.000 | U8: 2030 | V8: Seguro (até 2030) | W8: =COUNTIFS('Desempenho por Jogo (Logs)'!$G$5:$G$206, A8) -> 10 | X8: =COUNTIFS('Desempenho por Jogo (Logs)'!$G$5:$G$206, A8, 'Desempenho por Jogo (Logs)'!$J$5:$J$206, "<>RES") -> 9 | Y8: =COUNTIFS('Desempenho por Jogo (Logs)'!$G$5:$G$206, A8, 'Desempenho por Jogo (Logs)'!$J$5:$J$206, "RES") -> 1 | Z8: =SUMIFS('Desempenho por Jogo (Logs)'!$K$5:$K$206, 'Desempenho por Jogo (Logs)'!$G$5:$G$206, A8) -> 705 | AA8: =IF(Z8>0, Z8/540, 0) -> 0.603 | AB8: =SUMIFS('Desempenho por Jogo (Logs)'!$L$5:$L$206, 'Desempenho por Jogo (Logs)'!$G$5:$G$206, A8) -> 1 | AC8: 4 | AD8: =AB8+AC8 -> 5 | AE8: =IF(Z8>0, ROUND((AD8/Z8)*90, 2), 0) -> 0.64 | AF8: =SUMIFS('Desempenho por Jogo (Logs)'!$L$5:$L$206, 'Desempenho por Jogo (Logs)'!$G$5:$G$206, A8, 'Desempenho por Jogo (Logs)'!$C$5:$C$206, "*Liga*") -> 0 | AG8: 3 | AH8: =SUMIFS('Desempenho por Jogo (Logs)'!$L$5:$L$206, 'Desempenho por Jogo (Logs)'!$G$5:$G$206, A8, 'Desempenho por Jogo (Logs)'!$C$5:$C$206, "*Trophy*") -> 1 | AI8: 1 | AJ8: 1 | AK8: =IFERROR(ROUND(AVERAGEIFS('Desempenho por Jogo (Logs)'!$N$5:$N$206, 'Desempenho por Jogo (Logs)'!$G$5:$G$206, A8, 'Desempenho por Jogo (Logs)'!$N$5:$N$206, ">0"), 2), "S/N") -> 7.23 | AL8: Boa (7,00) | AM8: =IF(W8=0, "Nula (0 jogos)", IF(OR(W8<=2, Z8<150), "Baixa — Amostra Insuficiente", IF(AND(W8>=4, Z8>=240), "Alta", "Moderada"))) -> Alta (≥4J e ≥270m) | AN8: =IF(W8=0, "Sem minutagem no save", IF(OR(W8<=2, Z8<150), "Amostra insuficiente (" & W8 & "J / " & Z8 & "m) — Continuar observando", IF(AK8>=7.5, "Promover minutos / Titularidade em ascensão", IF(AK8>=7.0, "Manter minutagem atual", "Avaliar opções / Rotação")))) -> Titular Regular na Temporada — Manter | AO8: Titular com 705 min em 10J (60,3% do tempo possível, Nota 7,23) | AP8: Atleta de 24 anos (Espanha). posição MC (VOL). hierarquia atual 'Titular (MC)'. Overall 68 e Potencial 70 (margem de potencial +2; evolução real no save +1). Soma 705 min em 10 partidas (9T/1R). com 1 gol(s) verificado(s) por partida. 4 assistência(s) na temporada (5 G+A) e nota média 7.23. Vínculo: contrato até 2030 (Rodízio). avaliado em € 1.600.000.
A9: 275520 | B9: 8 | C9: Manu Bueno | D9: Manuel Bueno Sebastián | E9: Titular (MC) | F9: Titular Efetivo (43% min) | G9: Importante | H9: MC | I9: MEI, VOL | J9: Meio-Campo | K9: 67 | L9: 76 | M9: =L9-K9 -> 9 | N9: =K9-67 -> 0 | O9: 21 | P9: 28/07/2004 | Q9: Espanha | R9: 2700000 | S9: 10000 | T9: € 6.600.000 | U9: 2029 | V9: Seguro (até 2029) | W9: =COUNTIFS('Desempenho por Jogo (Logs)'!$G$5:$G$206, A9) -> 8 | X9: =COUNTIFS('Desempenho por Jogo (Logs)'!$G$5:$G$206, A9, 'Desempenho por Jogo (Logs)'!$J$5:$J$206, "<>RES") -> 7 | Y9: =COUNTIFS('Desempenho por Jogo (Logs)'!$G$5:$G$206, A9, 'Desempenho por Jogo (Logs)'!$J$5:$J$206, "RES") -> 1 | Z9: =SUMIFS('Desempenho por Jogo (Logs)'!$K$5:$K$206, 'Desempenho por Jogo (Logs)'!$G$5:$G$206, A9) -> 502 | AA9: =IF(Z9>0, Z9/540, 0) -> 0.429 | AB9: =SUMIFS('Desempenho por Jogo (Logs)'!$L$5:$L$206, 'Desempenho por Jogo (Logs)'!$G$5:$G$206, A9) -> 2 | AC9: 1 | AD9: =AB9+AC9 -> 3 | AE9: =IF(Z9>0, ROUND((AD9/Z9)*90, 2), 0) -> 0.54 | AF9: =SUMIFS('Desempenho por Jogo (Logs)'!$L$5:$L$206, 'Desempenho por Jogo (Logs)'!$G$5:$G$206, A9, 'Desempenho por Jogo (Logs)'!$C$5:$C$206, "*Liga*") -> 2 | AG9: 1 | AH9: =SUMIFS('Desempenho por Jogo (Logs)'!$L$5:$L$206, 'Desempenho por Jogo (Logs)'!$G$5:$G$206, A9, 'Desempenho por Jogo (Logs)'!$C$5:$C$206, "*Trophy*") -> 0 | AI9: 0 | AJ9: 0 | AK9: =IFERROR(ROUND(AVERAGEIFS('Desempenho por Jogo (Logs)'!$N$5:$N$206, 'Desempenho por Jogo (Logs)'!$G$5:$G$206, A9, 'Desempenho por Jogo (Logs)'!$N$5:$N$206, ">0"), 2), "S/N") -> 6.89 | AL9: Boa (7,02) | AM9: =IF(W9=0, "Nula (0 jogos)", IF(OR(W9<=2, Z9<150), "Baixa — Amostra Insuficiente", IF(AND(W9>=4, Z9>=240), "Alta", "Moderada"))) -> Alta (≥4J e ≥270m) | AN9: =IF(W9=0, "Sem minutagem no save", IF(OR(W9<=2, Z9<150), "Amostra insuficiente (" & W9 & "J / " & Z9 & "m) — Continuar observando", IF(AK9>=7.5, "Promover minutos / Titularidade em ascensão", IF(AK9>=7.0, "Manter minutagem atual", "Avaliar opções / Rotação")))) -> Titular Regular na Temporada — Manter | AO9: Titular com 502 min em 8J (42,9% do tempo possível, Nota 6,89) | AP9: Atleta de 21 anos (Espanha). posição MC (MEI. VOL). hierarquia atual 'Titular (MC)'. Overall 67 e Potencial 76 (margem de potencial +9; evolução real no save +0). Soma 502 min em 8 partidas (7T/1R). com 2 gol(s) verificado(s) por partida. 1 assistência(s) na temporada (3 G+A) e nota média 6.89. Vínculo: contrato até 2029 (Importante). avaliado em € 2.700.000.
A10: 247500 | B10: 12 | C10: Edgar González | D10: Edgar González Estrada | E10: Titular (ZAG) | F10: Titular Efetivo (80% min) | G10: Rodízio | H10: ZAG | I10: — | J10: Defesa | K10: 72 | L10: 72 | M10: =L10-K10 -> 0 | N10: =K10-71 -> 1 | O10: 28 | P10: 02/04/1997 | Q10: Espanha | R10: 2100000 | S10: 6900 | T10: Sem multa rescisória | U10: 2028 | V10: Seguro (até 2028) | W10: =COUNTIFS('Desempenho por Jogo (Logs)'!$G$5:$G$206, A10) -> 11 | X10: =COUNTIFS('Desempenho por Jogo (Logs)'!$G$5:$G$206, A10, 'Desempenho por Jogo (Logs)'!$J$5:$J$206, "<>RES") -> 11 | Y10: =COUNTIFS('Desempenho por Jogo (Logs)'!$G$5:$G$206, A10, 'Desempenho por Jogo (Logs)'!$J$5:$J$206, "RES") -> 0 | Z10: =SUMIFS('Desempenho por Jogo (Logs)'!$K$5:$K$206, 'Desempenho por Jogo (Logs)'!$G$5:$G$206, A10) -> 930 | AA10: =IF(Z10>0, Z10/540, 0) -> 0.795 | AB10: =SUMIFS('Desempenho por Jogo (Logs)'!$L$5:$L$206, 'Desempenho por Jogo (Logs)'!$G$5:$G$206, A10) -> 0 | AC10: 0 | AD10: =AB10+AC10 -> 0 | AE10: =IF(Z10>0, ROUND((AD10/Z10)*90, 2), 0) -> 0 | AF10: =SUMIFS('Desempenho por Jogo (Logs)'!$L$5:$L$206, 'Desempenho por Jogo (Logs)'!$G$5:$G$206, A10, 'Desempenho por Jogo (Logs)'!$C$5:$C$206, "*Liga*") -> 0 | AG10: 0 | AH10: =SUMIFS('Desempenho por Jogo (Logs)'!$L$5:$L$206, 'Desempenho por Jogo (Logs)'!$G$5:$G$206, A10, 'Desempenho por Jogo (Logs)'!$C$5:$C$206, "*Trophy*") -> 0 | AI10: 0 | AJ10: 0 | AK10: =IFERROR(ROUND(AVERAGEIFS('Desempenho por Jogo (Logs)'!$N$5:$N$206, 'Desempenho por Jogo (Logs)'!$G$5:$G$206, A10, 'Desempenho por Jogo (Logs)'!$N$5:$N$206, ">0"), 2), "S/N") -> 6.84 | AL10: Regular (6,80) | AM10: =IF(W10=0, "Nula (0 jogos)", IF(OR(W10<=2, Z10<150), "Baixa — Amostra Insuficiente", IF(AND(W10>=4, Z10>=240), "Alta", "Moderada"))) -> Alta (≥4J e ≥270m) | AN10: =IF(W10=0, "Sem minutagem no save", IF(OR(W10<=2, Z10<150), "Amostra insuficiente (" & W10 & "J / " & Z10 & "m) — Continuar observando", IF(AK10>=7.5, "Promover minutos / Titularidade em ascensão", IF(AK10>=7.0, "Manter minutagem atual", "Avaliar opções / Rotação")))) -> Titular Regular na Temporada — Manter | AO10: Titular com 930 min em 11J (79,5% do tempo possível, Nota 6,84) | AP10: Atleta de 28 anos (Espanha). posição ZAG. hierarquia atual 'Titular (ZAG)'. Overall 72 e Potencial 72 (margem de potencial +0; evolução real no save +1). Soma 930 min em 11 partidas (11T/0R). com 0 gol(s) verificado(s) por partida. 0 assistência(s) na temporada (0 G+A) e nota média 6.84. Vínculo: contrato até 2028 (Rodízio). avaliado em € 2.100.000.
A11: 278758 | B11: 16 | C11: Jastin | D11: Jastin García | E11: Titular (PE) | F11: Titular Efetivo (54% min) | G11: Rodízio | H11: ME | I11: PE | J11: Meio-Campo | K11: 69 | L11: 80 | M11: =L11-K11 -> 11 | N11: =K11-68 -> 1 | O11: 21 | P11: 16/01/2004 | Q11: Espanha | R11: 3500000 | S11: 3600 | T11: Emprestado (Sem multa) | U11: 2027 | V11: Empréstimo até Jun/2026 | W11: =COUNTIFS('Desempenho por Jogo (Logs)'!$G$5:$G$206, A11) -> 12 | X11: =COUNTIFS('Desempenho por Jogo (Logs)'!$G$5:$G$206, A11, 'Desempenho por Jogo (Logs)'!$J$5:$J$206, "<>RES") -> 7 | Y11: =COUNTIFS('Desempenho por Jogo (Logs)'!$G$5:$G$206, A11, 'Desempenho por Jogo (Logs)'!$J$5:$J$206, "RES") -> 5 | Z11: =SUMIFS('Desempenho por Jogo (Logs)'!$K$5:$K$206, 'Desempenho por Jogo (Logs)'!$G$5:$G$206, A11) -> 626 | AA11: =IF(Z11>0, Z11/540, 0) -> 0.535 | AB11: =SUMIFS('Desempenho por Jogo (Logs)'!$L$5:$L$206, 'Desempenho por Jogo (Logs)'!$G$5:$G$206, A11) -> 0 | AC11: 4 | AD11: =AB11+AC11 -> 4 | AE11: =IF(Z11>0, ROUND((AD11/Z11)*90, 2), 0) -> 0.58 | AF11: =SUMIFS('Desempenho por Jogo (Logs)'!$L$5:$L$206, 'Desempenho por Jogo (Logs)'!$G$5:$G$206, A11, 'Desempenho por Jogo (Logs)'!$C$5:$C$206, "*Liga*") -> 0 | AG11: 4 | AH11: =SUMIFS('Desempenho por Jogo (Logs)'!$L$5:$L$206, 'Desempenho por Jogo (Logs)'!$G$5:$G$206, A11, 'Desempenho por Jogo (Logs)'!$C$5:$C$206, "*Trophy*") -> 0 | AI11: 0 | AJ11: 1 | AK11: =IFERROR(ROUND(AVERAGEIFS('Desempenho por Jogo (Logs)'!$N$5:$N$206, 'Desempenho por Jogo (Logs)'!$G$5:$G$206, A11, 'Desempenho por Jogo (Logs)'!$N$5:$N$206, ">0"), 2), "S/N") -> 7.28 | AL11: Boa (7,14) | AM11: =IF(W11=0, "Nula (0 jogos)", IF(OR(W11<=2, Z11<150), "Baixa — Amostra Insuficiente", IF(AND(W11>=4, Z11>=240), "Alta", "Moderada"))) -> Alta (≥4J e ≥270m) | AN11: =IF(W11=0, "Sem minutagem no save", IF(OR(W11<=2, Z11<150), "Amostra insuficiente (" & W11 & "J / " & Z11 & "m) — Continuar observando", IF(AK11>=7.5, "Promover minutos / Titularidade em ascensão", IF(AK11>=7.0, "Manter minutagem atual", "Avaliar opções / Rotação")))) -> Jovem em Desenvolvimento Ativo — Manter Minutagem | AO11: 21 anos, POT 80 (+11 margem) e 626 min disputados (12J) | AP11: Atleta de 21 anos (Espanha). posição ME (PE). hierarquia atual 'Titular (PE)'. Overall 69 e Potencial 80 (margem de potencial +11; evolução real no save +1). Soma 626 min em 12 partidas (7T/5R). com 0 gol(s) verificado(s) por partida. 4 assistência(s) na temporada (4 G+A) e nota média 7.28. Vínculo: atleta emprestado ao clube até 2026. avaliado em € 3.500.000.
A12: 263006 | B12: 19 | C12: Imanol | D12: Imanol García de Albéniz | E12: Titular (LD) | F12: Titular Efetivo (57% min) | G12: Rodízio | H12: LE | I12: ME | J12: Defesa | K12: 71 | L12: 73 | M12: =L12-K12 -> 2 | N12: =K12-70 -> 1 | O12: 25 | P12: 09/06/2000 | Q12: Espanha | R12: 2300000 | S12: 5600 | T12: Sem multa rescisória | U12: 2029 | V12: Seguro (até 2029) | W12: =COUNTIFS('Desempenho por Jogo (Logs)'!$G$5:$G$206, A12) -> 11 | X12: =COUNTIFS('Desempenho por Jogo (Logs)'!$G$5:$G$206, A12, 'Desempenho por Jogo (Logs)'!$J$5:$J$206, "<>RES") -> 10 | Y12: =COUNTIFS('Desempenho por Jogo (Logs)'!$G$5:$G$206, A12, 'Desempenho por Jogo (Logs)'!$J$5:$J$206, "RES") -> 1 | Z12: =SUMIFS('Desempenho por Jogo (Logs)'!$K$5:$K$206, 'Desempenho por Jogo (Logs)'!$G$5:$G$206, A12) -> 669 | AA12: =IF(Z12>0, Z12/540, 0) -> 0.572 | AB12: =SUMIFS('Desempenho por Jogo (Logs)'!$L$5:$L$206, 'Desempenho por Jogo (Logs)'!$G$5:$G$206, A12) -> 1 | AC12: 2 | AD12: =AB12+AC12 -> 3 | AE12: =IF(Z12>0, ROUND((AD12/Z12)*90, 2), 0) -> 0.4 | AF12: =SUMIFS('Desempenho por Jogo (Logs)'!$L$5:$L$206, 'Desempenho por Jogo (Logs)'!$G$5:$G$206, A12, 'Desempenho por Jogo (Logs)'!$C$5:$C$206, "*Liga*") -> 0 | AG12: 2 | AH12: =SUMIFS('Desempenho por Jogo (Logs)'!$L$5:$L$206, 'Desempenho por Jogo (Logs)'!$G$5:$G$206, A12, 'Desempenho por Jogo (Logs)'!$C$5:$C$206, "*Trophy*") -> 1 | AI12: 0 | AJ12: 0 | AK12: =IFERROR(ROUND(AVERAGEIFS('Desempenho por Jogo (Logs)'!$N$5:$N$206, 'Desempenho por Jogo (Logs)'!$G$5:$G$206, A12, 'Desempenho por Jogo (Logs)'!$N$5:$N$206, ">0"), 2), "S/N") -> 6.9 | AL12: Regular (6,64) | AM12: =IF(W12=0, "Nula (0 jogos)", IF(OR(W12<=2, Z12<150), "Baixa — Amostra Insuficiente", IF(AND(W12>=4, Z12>=240), "Alta", "Moderada"))) -> Alta (≥4J e ≥270m) | AN12: =IF(W12=0, "Sem minutagem no save", IF(OR(W12<=2, Z12<150), "Amostra insuficiente (" & W12 & "J / " & Z12 & "m) — Continuar observando", IF(AK12>=7.5, "Promover minutos / Titularidade em ascensão", IF(AK12>=7.0, "Manter minutagem atual", "Avaliar opções / Rotação")))) -> Titular Regular na Temporada — Manter | AO12: Titular com 669 min em 11J (57,2% do tempo possível, Nota 6,90) | AP12: Atleta de 25 anos (Espanha). posição LE (ME). hierarquia atual 'Titular (LD)'. Overall 71 e Potencial 73 (margem de potencial +2; evolução real no save +1). Soma 669 min em 11 partidas (10T/1R). com 1 gol(s) verificado(s) por partida. 2 assistência(s) na temporada (3 G+A) e nota média 6.90. Vínculo: contrato até 2029 (Rodízio). avaliado em € 2.300.000.
A13: 279881 | B13: 21 | C13: Efe Akman | D13: Efe Akman | E13: Titular (MC) | F13: Titular Efetivo (63% min) | G13: Rodízio | H13: MC | I13: VOL | J13: Meio-Campo | K13: 65 | L13: 78 | M13: =L13-K13 -> 13 | N13: =K13-64 -> 1 | O13: 19 | P13: 21/03/2006 | Q13: Turquia | R13: 1600000 | S13: 1900 | T13: € 3.500.000 | U13: 2029 | V13: Seguro (até 2029) | W13: =COUNTIFS('Desempenho por Jogo (Logs)'!$G$5:$G$206, A13) -> 9 | X13: =COUNTIFS('Desempenho por Jogo (Logs)'!$G$5:$G$206, A13, 'Desempenho por Jogo (Logs)'!$J$5:$J$206, "<>RES") -> 9 | Y13: =COUNTIFS('Desempenho por Jogo (Logs)'!$G$5:$G$206, A13, 'Desempenho por Jogo (Logs)'!$J$5:$J$206, "RES") -> 0 | Z13: =SUMIFS('Desempenho por Jogo (Logs)'!$K$5:$K$206, 'Desempenho por Jogo (Logs)'!$G$5:$G$206, A13) -> 735 | AA13: =IF(Z13>0, Z13/540, 0) -> 0.628 | AB13: =SUMIFS('Desempenho por Jogo (Logs)'!$L$5:$L$206, 'Desempenho por Jogo (Logs)'!$G$5:$G$206, A13) -> 0 | AC13: 3 | AD13: =AB13+AC13 -> 3 | AE13: =IF(Z13>0, ROUND((AD13/Z13)*90, 2), 0) -> 0.37 | AF13: =SUMIFS('Desempenho por Jogo (Logs)'!$L$5:$L$206, 'Desempenho por Jogo (Logs)'!$G$5:$G$206, A13, 'Desempenho por Jogo (Logs)'!$C$5:$C$206, "*Liga*") -> 0 | AG13: 2 | AH13: =SUMIFS('Desempenho por Jogo (Logs)'!$L$5:$L$206, 'Desempenho por Jogo (Logs)'!$G$5:$G$206, A13, 'Desempenho por Jogo (Logs)'!$C$5:$C$206, "*Trophy*") -> 0 | AI13: 1 | AJ13: 0 | AK13: =IFERROR(ROUND(AVERAGEIFS('Desempenho por Jogo (Logs)'!$N$5:$N$206, 'Desempenho por Jogo (Logs)'!$G$5:$G$206, A13, 'Desempenho por Jogo (Logs)'!$N$5:$N$206, ">0"), 2), "S/N") -> 7.82 | AL13: Boa (7,00) | AM13: =IF(W13=0, "Nula (0 jogos)", IF(OR(W13<=2, Z13<150), "Baixa — Amostra Insuficiente", IF(AND(W13>=4, Z13>=240), "Alta", "Moderada"))) -> Alta (≥4J e ≥270m) | AN13: =IF(W13=0, "Sem minutagem no save", IF(OR(W13<=2, Z13<150), "Amostra insuficiente (" & W13 & "J / " & Z13 & "m) — Continuar observando", IF(AK13>=7.5, "Promover minutos / Titularidade em ascensão", IF(AK13>=7.0, "Manter minutagem atual", "Avaliar opções / Rotação")))) -> Jovem em Desenvolvimento Ativo — Manter Minutagem | AO13: 19 anos, POT 78 (+13 margem) e 735 min disputados (9J) | AP13: Atleta de 19 anos (Turquia). posição MC (VOL). hierarquia atual 'Titular (MC)'. Overall 65 e Potencial 78 (margem de potencial +13; evolução real no save +1). Soma 735 min em 9 partidas (9T/0R). com 0 gol(s) verificado(s) por partida. 3 assistência(s) na temporada (3 G+A) e nota média 7.82. Vínculo: contrato até 2029 (Rodízio). avaliado em € 1.600.000.
A14: 236393 | B14: 22 | C14: Marc Cardona | D14: Marc Cardona Rovira | E14: Titular (ATA) | F14: Titular Efetivo (54% min) | G14: Rodízio | H14: ATA | I14: MD | J14: Ataque | K14: 67 | L14: 67 | M14: =L14-K14 -> 0 | N14: =K14-67 -> 0 | O14: 30 | P14: 09/07/1995 | Q14: Espanha | R14: 1200000 | S14: 4800 | T14: Sem multa rescisória | U14: 2028 | V14: Seguro (até 2028) | W14: =COUNTIFS('Desempenho por Jogo (Logs)'!$G$5:$G$206, A14) -> 9 | X14: =COUNTIFS('Desempenho por Jogo (Logs)'!$G$5:$G$206, A14, 'Desempenho por Jogo (Logs)'!$J$5:$J$206, "<>RES") -> 7 | Y14: =COUNTIFS('Desempenho por Jogo (Logs)'!$G$5:$G$206, A14, 'Desempenho por Jogo (Logs)'!$J$5:$J$206, "RES") -> 2 | Z14: =SUMIFS('Desempenho por Jogo (Logs)'!$K$5:$K$206, 'Desempenho por Jogo (Logs)'!$G$5:$G$206, A14) -> 637 | AA14: =IF(Z14>0, Z14/540, 0) -> 0.544 | AB14: =SUMIFS('Desempenho por Jogo (Logs)'!$L$5:$L$206, 'Desempenho por Jogo (Logs)'!$G$5:$G$206, A14) -> 15 | AC14: 1 | AD14: =AB14+AC14 -> 16 | AE14: =IF(Z14>0, ROUND((AD14/Z14)*90, 2), 0) -> 2.26 | AF14: =SUMIFS('Desempenho por Jogo (Logs)'!$L$5:$L$206, 'Desempenho por Jogo (Logs)'!$G$5:$G$206, A14, 'Desempenho por Jogo (Logs)'!$C$5:$C$206, "*Liga*") -> 15 | AG14: 0 | AH14: =SUMIFS('Desempenho por Jogo (Logs)'!$L$5:$L$206, 'Desempenho por Jogo (Logs)'!$G$5:$G$206, A14, 'Desempenho por Jogo (Logs)'!$C$5:$C$206, "*Trophy*") -> 0 | AI14: 1 | AJ14: 3 | AK14: =IFERROR(ROUND(AVERAGEIFS('Desempenho por Jogo (Logs)'!$N$5:$N$206, 'Desempenho por Jogo (Logs)'!$G$5:$G$206, A14, 'Desempenho por Jogo (Logs)'!$N$5:$N$206, ">0"), 2), "S/N") -> 8.27 | AL14: Excelente (8,34) | AM14: =IF(W14=0, "Nula (0 jogos)", IF(OR(W14<=2, Z14<150), "Baixa — Amostra Insuficiente", IF(AND(W14>=4, Z14>=240), "Alta", "Moderada"))) -> Alta (≥4J e ≥270m) | AN14: =IF(W14=0, "Sem minutagem no save", IF(OR(W14<=2, Z14<150), "Amostra insuficiente (" & W14 & "J / " & Z14 & "m) — Continuar observando", IF(AK14>=7.5, "Promover minutos / Titularidade em ascensão", IF(AK14>=7.0, "Manter minutagem atual", "Avaliar opções / Rotação")))) -> Titular Regular na Temporada — Manter | AO14: Titular com 637 min em 9J (54,4% do tempo possível, Nota 8,27) | AP14: Atleta de 30 anos (Espanha). posição ATA (MD). hierarquia atual 'Titular (ATA)'. Overall 67 e Potencial 67 (margem de potencial +0; evolução real no save +0). Soma 637 min em 9 partidas (7T/2R). com 15 gol(s) verificado(s) por partida. 1 assistência(s) na temporada (16 G+A) e nota média 8.27. Vínculo: contrato até 2028 (Rodízio). avaliado em € 1.200.000.
A15: 276198 | B15: 25 | C15: Áron Yaakobishvili | D15: Áron Yaakobishvili | E15: Titular (GOL) | F15: Titular Efetivo (62% min) | G15: Rodízio | H15: GOL | I15: — | J15: Goleiro | K15: 72 | L15: 82 | M15: =L15-K15 -> 10 | N15: =K15-70 -> 2 | O15: 19 | P15: 07/03/2006 | Q15: Hungria | R15: 3900000 | S15: 1900 | T15: Emprestado (Sem multa) | U15: 2028 | V15: Empréstimo até Jun/2026 | W15: =COUNTIFS('Desempenho por Jogo (Logs)'!$G$5:$G$206, A15) -> 8 | X15: =COUNTIFS('Desempenho por Jogo (Logs)'!$G$5:$G$206, A15, 'Desempenho por Jogo (Logs)'!$J$5:$J$206, "<>RES") -> 8 | Y15: =COUNTIFS('Desempenho por Jogo (Logs)'!$G$5:$G$206, A15, 'Desempenho por Jogo (Logs)'!$J$5:$J$206, "RES") -> 0 | Z15: =SUMIFS('Desempenho por Jogo (Logs)'!$K$5:$K$206, 'Desempenho por Jogo (Logs)'!$G$5:$G$206, A15) -> 720 | AA15: =IF(Z15>0, Z15/540, 0) -> 0.615 | AB15: =SUMIFS('Desempenho por Jogo (Logs)'!$L$5:$L$206, 'Desempenho por Jogo (Logs)'!$G$5:$G$206, A15) -> 0 | AC15: 0 | AD15: =AB15+AC15 -> 0 | AE15: =IF(Z15>0, ROUND((AD15/Z15)*90, 2), 0) -> 0 | AF15: =SUMIFS('Desempenho por Jogo (Logs)'!$L$5:$L$206, 'Desempenho por Jogo (Logs)'!$G$5:$G$206, A15, 'Desempenho por Jogo (Logs)'!$C$5:$C$206, "*Liga*") -> 0 | AG15: 0 | AH15: =SUMIFS('Desempenho por Jogo (Logs)'!$L$5:$L$206, 'Desempenho por Jogo (Logs)'!$G$5:$G$206, A15, 'Desempenho por Jogo (Logs)'!$C$5:$C$206, "*Trophy*") -> 0 | AI15: 0 | AJ15: 1 | AK15: =IFERROR(ROUND(AVERAGEIFS('Desempenho por Jogo (Logs)'!$N$5:$N$206, 'Desempenho por Jogo (Logs)'!$G$5:$G$206, A15, 'Desempenho por Jogo (Logs)'!$N$5:$N$206, ">0"), 2), "S/N") -> 6.84 | AL15: Regular (6,60) | AM15: =IF(W15=0, "Nula (0 jogos)", IF(OR(W15<=2, Z15<150), "Baixa — Amostra Insuficiente", IF(AND(W15>=4, Z15>=240), "Alta", "Moderada"))) -> Alta (≥4J e ≥270m) | AN15: =IF(W15=0, "Sem minutagem no save", IF(OR(W15<=2, Z15<150), "Amostra insuficiente (" & W15 & "J / " & Z15 & "m) — Continuar observando", IF(AK15>=7.5, "Promover minutos / Titularidade em ascensão", IF(AK15>=7.0, "Manter minutagem atual", "Avaliar opções / Rotação")))) -> Jovem em Desenvolvimento Ativo — Manter Minutagem | AO15: 19 anos, POT 82 (+10 margem) e 720 min disputados (8J) | AP15: Atleta de 19 anos (Hungria). posição GOL. hierarquia atual 'Titular (GOL)'. Overall 72 e Potencial 82 (margem de potencial +10; evolução real no save +2). Soma 720 min em 8 partidas (8T/0R). com 0 gol(s) verificado(s) por partida. 0 assistência(s) na temporada (0 G+A) e nota média 6.84. Vínculo: atleta emprestado ao clube até 2026. avaliado em € 3.900.000.
A16: 79703 | B16: 4 | C16: Gaël Alonso | D16: Gaël Alonso Moreno | E16: Suplente (Banco) | F16: Rotação Ativa (24% min) | G16: Rodízio | H16: ZAG | I16: — | J16: Defesa | K16: 67 | L16: 74 | M16: =L16-K16 -> 7 | N16: =K16-66 -> 1 | O16: 23 | P16: 23/07/2002 | Q16: Espanha | R16: 2100000 | S16: 3000 | T16: Sem multa rescisória | U16: 2028 | V16: Seguro (até 2028) | W16: =COUNTIFS('Desempenho por Jogo (Logs)'!$G$5:$G$206, A16) -> 5 | X16: =COUNTIFS('Desempenho por Jogo (Logs)'!$G$5:$G$206, A16, 'Desempenho por Jogo (Logs)'!$J$5:$J$206, "<>RES") -> 4 | Y16: =COUNTIFS('Desempenho por Jogo (Logs)'!$G$5:$G$206, A16, 'Desempenho por Jogo (Logs)'!$J$5:$J$206, "RES") -> 1 | Z16: =SUMIFS('Desempenho por Jogo (Logs)'!$K$5:$K$206, 'Desempenho por Jogo (Logs)'!$G$5:$G$206, A16) -> 286 | AA16: =IF(Z16>0, Z16/540, 0) -> 0.244 | AB16: =SUMIFS('Desempenho por Jogo (Logs)'!$L$5:$L$206, 'Desempenho por Jogo (Logs)'!$G$5:$G$206, A16) -> 0 | AC16: 0 | AD16: =AB16+AC16 -> 0 | AE16: =IF(Z16>0, ROUND((AD16/Z16)*90, 2), 0) -> 0 | AF16: =SUMIFS('Desempenho por Jogo (Logs)'!$L$5:$L$206, 'Desempenho por Jogo (Logs)'!$G$5:$G$206, A16, 'Desempenho por Jogo (Logs)'!$C$5:$C$206, "*Liga*") -> 0 | AG16: 0 | AH16: =SUMIFS('Desempenho por Jogo (Logs)'!$L$5:$L$206, 'Desempenho por Jogo (Logs)'!$G$5:$G$206, A16, 'Desempenho por Jogo (Logs)'!$C$5:$C$206, "*Trophy*") -> 0 | AI16: 0 | AJ16: 0 | AK16: =IFERROR(ROUND(AVERAGEIFS('Desempenho por Jogo (Logs)'!$N$5:$N$206, 'Desempenho por Jogo (Logs)'!$G$5:$G$206, A16, 'Desempenho por Jogo (Logs)'!$N$5:$N$206, ">0"), 2), "S/N") -> 6.18 | AL16: Oscilante (6,18) | AM16: =IF(W16=0, "Nula (0 jogos)", IF(OR(W16<=2, Z16<150), "Baixa — Amostra Insuficiente", IF(AND(W16>=4, Z16>=240), "Alta", "Moderada"))) -> Alta (≥4J e ≥270m) | AN16: =IF(W16=0, "Sem minutagem no save", IF(OR(W16<=2, Z16<150), "Amostra insuficiente (" & W16 & "J / " & Z16 & "m) — Continuar observando", IF(AK16>=7.5, "Promover minutos / Titularidade em ascensão", IF(AK16>=7.0, "Manter minutagem atual", "Avaliar opções / Rotação")))) -> Manter na Rotação do Elenco | AO16: Participação regular na rotação (286 min em 5J, OVR 67) | AP16: Atleta de 23 anos (Espanha). posição ZAG. hierarquia atual 'Suplente (Banco)'. Overall 67 e Potencial 74 (margem de potencial +7; evolução real no save +1). Soma 286 min em 5 partidas (4T/1R). com 0 gol(s) verificado(s) por partida. 0 assistência(s) na temporada (0 G+A) e nota média 6.18. Vínculo: contrato até 2028 (Rodízio). avaliado em € 2.100.000.
A17: 265405 | B17: 13 | C17: Jesús Owono | D17: Jesús Lázaro Owono Ngua Akeng | E17: Suplente (Banco) | F17: Titular Efetivo (38% min) | G17: Rodízio | H17: GOL | I17: — | J17: Goleiro | K17: 68 | L17: 73 | M17: =L17-K17 -> 5 | N17: =K17-67 -> 1 | O17: 24 | P17: 02/03/2001 | Q17: Guiné Equatorial | R17: 1500000 | S17: 2000 | T17: Sem multa rescisória | U17: 2029 | V17: Seguro (até 2029) | W17: =COUNTIFS('Desempenho por Jogo (Logs)'!$G$5:$G$206, A17) -> 5 | X17: =COUNTIFS('Desempenho por Jogo (Logs)'!$G$5:$G$206, A17, 'Desempenho por Jogo (Logs)'!$J$5:$J$206, "<>RES") -> 5 | Y17: =COUNTIFS('Desempenho por Jogo (Logs)'!$G$5:$G$206, A17, 'Desempenho por Jogo (Logs)'!$J$5:$J$206, "RES") -> 0 | Z17: =SUMIFS('Desempenho por Jogo (Logs)'!$K$5:$K$206, 'Desempenho por Jogo (Logs)'!$G$5:$G$206, A17) -> 450 | AA17: =IF(Z17>0, Z17/540, 0) -> 0.385 | AB17: =SUMIFS('Desempenho por Jogo (Logs)'!$L$5:$L$206, 'Desempenho por Jogo (Logs)'!$G$5:$G$206, A17) -> 0 | AC17: 0 | AD17: =AB17+AC17 -> 0 | AE17: =IF(Z17>0, ROUND((AD17/Z17)*90, 2), 0) -> 0 | AF17: =SUMIFS('Desempenho por Jogo (Logs)'!$L$5:$L$206, 'Desempenho por Jogo (Logs)'!$G$5:$G$206, A17, 'Desempenho por Jogo (Logs)'!$C$5:$C$206, "*Liga*") -> 0 | AG17: 0 | AH17: =SUMIFS('Desempenho por Jogo (Logs)'!$L$5:$L$206, 'Desempenho por Jogo (Logs)'!$G$5:$G$206, A17, 'Desempenho por Jogo (Logs)'!$C$5:$C$206, "*Trophy*") -> 0 | AI17: 0 | AJ17: 0 | AK17: =IFERROR(ROUND(AVERAGEIFS('Desempenho por Jogo (Logs)'!$N$5:$N$206, 'Desempenho por Jogo (Logs)'!$G$5:$G$206, A17, 'Desempenho por Jogo (Logs)'!$N$5:$N$206, ">0"), 2), "S/N") -> 6.6 | AL17: Regular (6,60) | AM17: =IF(W17=0, "Nula (0 jogos)", IF(OR(W17<=2, Z17<150), "Baixa — Amostra Insuficiente", IF(AND(W17>=4, Z17>=240), "Alta", "Moderada"))) -> Alta (≥4J e ≥270m) | AN17: =IF(W17=0, "Sem minutagem no save", IF(OR(W17<=2, Z17<150), "Amostra insuficiente (" & W17 & "J / " & Z17 & "m) — Continuar observando", IF(AK17>=7.5, "Promover minutos / Titularidade em ascensão", IF(AK17>=7.0, "Manter minutagem atual", "Avaliar opções / Rotação")))) -> Manter na Rotação do Elenco | AO17: Participação regular na rotação (450 min em 5J, OVR 68) | AP17: Atleta de 24 anos (Guiné Equatorial). posição GOL. hierarquia atual 'Suplente (Banco)'. Overall 68 e Potencial 73 (margem de potencial +5; evolução real no save +1). Soma 450 min em 5 partidas (5T/0R). com 0 gol(s) verificado(s) por partida. 0 assistência(s) na temporada (0 G+A) e nota média 6.60. Vínculo: contrato até 2029 (Rodízio). avaliado em € 1.500.000.
A18: 230134 | B18: 14 | C18: Sergio Molina | D18: Sergio Molina Beloqui | E18: Suplente (Banco) | F18: Titular Efetivo (44% min) | G18: Rodízio | H18: MC | I18: VOL, ZAG | J18: Meio-Campo | K18: 66 | L18: 66 | M18: =L18-K18 -> 0 | N18: =K18-66 -> 0 | O18: 29 | P18: 19/02/1996 | Q18: Espanha | R18: 975000 | S18: 3800 | T18: Sem multa rescisória | U18: 2028 | V18: Seguro (até 2028) | W18: =COUNTIFS('Desempenho por Jogo (Logs)'!$G$5:$G$206, A18) -> 10 | X18: =COUNTIFS('Desempenho por Jogo (Logs)'!$G$5:$G$206, A18, 'Desempenho por Jogo (Logs)'!$J$5:$J$206, "<>RES") -> 6 | Y18: =COUNTIFS('Desempenho por Jogo (Logs)'!$G$5:$G$206, A18, 'Desempenho por Jogo (Logs)'!$J$5:$J$206, "RES") -> 4 | Z18: =SUMIFS('Desempenho por Jogo (Logs)'!$K$5:$K$206, 'Desempenho por Jogo (Logs)'!$G$5:$G$206, A18) -> 514 | AA18: =IF(Z18>0, Z18/540, 0) -> 0.439 | AB18: =SUMIFS('Desempenho por Jogo (Logs)'!$L$5:$L$206, 'Desempenho por Jogo (Logs)'!$G$5:$G$206, A18) -> 3 | AC18: 0 | AD18: =AB18+AC18 -> 3 | AE18: =IF(Z18>0, ROUND((AD18/Z18)*90, 2), 0) -> 0.53 | AF18: =SUMIFS('Desempenho por Jogo (Logs)'!$L$5:$L$206, 'Desempenho por Jogo (Logs)'!$G$5:$G$206, A18, 'Desempenho por Jogo (Logs)'!$C$5:$C$206, "*Liga*") -> 3 | AG18: 0 | AH18: =SUMIFS('Desempenho por Jogo (Logs)'!$L$5:$L$206, 'Desempenho por Jogo (Logs)'!$G$5:$G$206, A18, 'Desempenho por Jogo (Logs)'!$C$5:$C$206, "*Trophy*") -> 0 | AI18: 0 | AJ18: 0 | AK18: =IFERROR(ROUND(AVERAGEIFS('Desempenho por Jogo (Logs)'!$N$5:$N$206, 'Desempenho por Jogo (Logs)'!$G$5:$G$206, A18, 'Desempenho por Jogo (Logs)'!$N$5:$N$206, ">0"), 2), "S/N") -> 7.16 | AL18: Boa (7,02) | AM18: =IF(W18=0, "Nula (0 jogos)", IF(OR(W18<=2, Z18<150), "Baixa — Amostra Insuficiente", IF(AND(W18>=4, Z18>=240), "Alta", "Moderada"))) -> Alta (≥4J e ≥270m) | AN18: =IF(W18=0, "Sem minutagem no save", IF(OR(W18<=2, Z18<150), "Amostra insuficiente (" & W18 & "J / " & Z18 & "m) — Continuar observando", IF(AK18>=7.5, "Promover minutos / Titularidade em ascensão", IF(AK18>=7.0, "Manter minutagem atual", "Avaliar opções / Rotação")))) -> Manter na Rotação do Elenco | AO18: Participação regular na rotação (514 min em 10J, OVR 66) | AP18: Atleta de 29 anos (Espanha). posição MC (VOL. ZAG). hierarquia atual 'Suplente (Banco)'. Overall 66 e Potencial 66 (margem de potencial +0; evolução real no save +0). Soma 514 min em 10 partidas (6T/4R). com 3 gol(s) verificado(s) por partida. 0 assistência(s) na temporada (3 G+A) e nota média 7.16. Vínculo: contrato até 2028 (Rodízio). avaliado em € 975.000.
A19: 279603 | B19: 15 | C19: Aingeru Olabarrieta | D19: Aingeru Olabarrieta Capelo | E19: Suplente (Banco) | F19: Titular Efetivo (40% min) | G19: Rodízio | H19: PD | I19: MD | J19: Ataque | K19: 69 | L19: 81 | M19: =L19-K19 -> 12 | N19: =K19-67 -> 2 | O19: 19 | P19: 15/11/2005 | Q19: Espanha | R19: 2900000 | S19: 3300 | T19: Emprestado (Sem multa) | U19: 2029 | V19: Empréstimo até Jun/2026 | W19: =COUNTIFS('Desempenho por Jogo (Logs)'!$G$5:$G$206, A19) -> 9 | X19: =COUNTIFS('Desempenho por Jogo (Logs)'!$G$5:$G$206, A19, 'Desempenho por Jogo (Logs)'!$J$5:$J$206, "<>RES") -> 6 | Y19: =COUNTIFS('Desempenho por Jogo (Logs)'!$G$5:$G$206, A19, 'Desempenho por Jogo (Logs)'!$J$5:$J$206, "RES") -> 3 | Z19: =SUMIFS('Desempenho por Jogo (Logs)'!$K$5:$K$206, 'Desempenho por Jogo (Logs)'!$G$5:$G$206, A19) -> 467 | AA19: =IF(Z19>0, Z19/540, 0) -> 0.399 | AB19: =SUMIFS('Desempenho por Jogo (Logs)'!$L$5:$L$206, 'Desempenho por Jogo (Logs)'!$G$5:$G$206, A19) -> 1 | AC19: 3 | AD19: =AB19+AC19 -> 4 | AE19: =IF(Z19>0, ROUND((AD19/Z19)*90, 2), 0) -> 0.77 | AF19: =SUMIFS('Desempenho por Jogo (Logs)'!$L$5:$L$206, 'Desempenho por Jogo (Logs)'!$G$5:$G$206, A19, 'Desempenho por Jogo (Logs)'!$C$5:$C$206, "*Liga*") -> 1 | AG19: 2 | AH19: =SUMIFS('Desempenho por Jogo (Logs)'!$L$5:$L$206, 'Desempenho por Jogo (Logs)'!$G$5:$G$206, A19, 'Desempenho por Jogo (Logs)'!$C$5:$C$206, "*Trophy*") -> 0 | AI19: 1 | AJ19: 1 | AK19: =IFERROR(ROUND(AVERAGEIFS('Desempenho por Jogo (Logs)'!$N$5:$N$206, 'Desempenho por Jogo (Logs)'!$G$5:$G$206, A19, 'Desempenho por Jogo (Logs)'!$N$5:$N$206, ">0"), 2), "S/N") -> 6.69 | AL19: Regular (6,78) | AM19: =IF(W19=0, "Nula (0 jogos)", IF(OR(W19<=2, Z19<150), "Baixa — Amostra Insuficiente", IF(AND(W19>=4, Z19>=240), "Alta", "Moderada"))) -> Alta (≥4J e ≥270m) | AN19: =IF(W19=0, "Sem minutagem no save", IF(OR(W19<=2, Z19<150), "Amostra insuficiente (" & W19 & "J / " & Z19 & "m) — Continuar observando", IF(AK19>=7.5, "Promover minutos / Titularidade em ascensão", IF(AK19>=7.0, "Manter minutagem atual", "Avaliar opções / Rotação")))) -> Jovem em Desenvolvimento Ativo — Manter Minutagem | AO19: 19 anos, POT 81 (+12 margem) e 467 min disputados (9J) | AP19: Atleta de 19 anos (Espanha). posição PD (MD). hierarquia atual 'Suplente (Banco)'. Overall 69 e Potencial 81 (margem de potencial +12; evolução real no save +2). Soma 467 min em 9 partidas (6T/3R). com 1 gol(s) verificado(s) por partida. 3 assistência(s) na temporada (4 G+A) e nota média 6.69. Vínculo: atleta emprestado ao clube até 2026. avaliado em € 2.900.000.
A20: 241505 | B20: 17 | C20: Thomas Carrique | D20: Thomas Carrique | E20: Suplente (Banco) | F20: Titular Efetivo (50% min) | G20: Rodízio | H20: LD | I20: MD | J20: Defesa | K20: 67 | L20: 67 | M20: =L20-K20 -> 0 | N20: =K20-66 -> 1 | O20: 26 | P20: 27/02/1999 | Q20: França | R20: 1100000 | S20: 3500 | T20: € 1.800.000 | U20: 2027 | V20: Atenção: Expira em 2027 (2 anos) | W20: =COUNTIFS('Desempenho por Jogo (Logs)'!$G$5:$G$206, A20) -> 10 | X20: =COUNTIFS('Desempenho por Jogo (Logs)'!$G$5:$G$206, A20, 'Desempenho por Jogo (Logs)'!$J$5:$J$206, "<>RES") -> 8 | Y20: =COUNTIFS('Desempenho por Jogo (Logs)'!$G$5:$G$206, A20, 'Desempenho por Jogo (Logs)'!$J$5:$J$206, "RES") -> 2 | Z20: =SUMIFS('Desempenho por Jogo (Logs)'!$K$5:$K$206, 'Desempenho por Jogo (Logs)'!$G$5:$G$206, A20) -> 581 | AA20: =IF(Z20>0, Z20/540, 0) -> 0.497 | AB20: =SUMIFS('Desempenho por Jogo (Logs)'!$L$5:$L$206, 'Desempenho por Jogo (Logs)'!$G$5:$G$206, A20) -> 0 | AC20: 2 | AD20: =AB20+AC20 -> 2 | AE20: =IF(Z20>0, ROUND((AD20/Z20)*90, 2), 0) -> 0.31 | AF20: =SUMIFS('Desempenho por Jogo (Logs)'!$L$5:$L$206, 'Desempenho por Jogo (Logs)'!$G$5:$G$206, A20, 'Desempenho por Jogo (Logs)'!$C$5:$C$206, "*Liga*") -> 0 | AG20: 2 | AH20: =SUMIFS('Desempenho por Jogo (Logs)'!$L$5:$L$206, 'Desempenho por Jogo (Logs)'!$G$5:$G$206, A20, 'Desempenho por Jogo (Logs)'!$C$5:$C$206, "*Trophy*") -> 0 | AI20: 0 | AJ20: 0 | AK20: =IFERROR(ROUND(AVERAGEIFS('Desempenho por Jogo (Logs)'!$N$5:$N$206, 'Desempenho por Jogo (Logs)'!$G$5:$G$206, A20, 'Desempenho por Jogo (Logs)'!$N$5:$N$206, ">0"), 2), "S/N") -> 6.72 | AL20: Regular (6,90) | AM20: =IF(W20=0, "Nula (0 jogos)", IF(OR(W20<=2, Z20<150), "Baixa — Amostra Insuficiente", IF(AND(W20>=4, Z20>=240), "Alta", "Moderada"))) -> Alta (≥4J e ≥270m) | AN20: =IF(W20=0, "Sem minutagem no save", IF(OR(W20<=2, Z20<150), "Amostra insuficiente (" & W20 & "J / " & Z20 & "m) — Continuar observando", IF(AK20>=7.5, "Promover minutos / Titularidade em ascensão", IF(AK20>=7.0, "Manter minutagem atual", "Avaliar opções / Rotação")))) -> Manter na Rotação do Elenco | AO20: Participação regular na rotação (581 min em 10J, OVR 67) | AP20: Atleta de 26 anos (França). posição LD (MD). hierarquia atual 'Suplente (Banco)'. Overall 67 e Potencial 67 (margem de potencial +0; evolução real no save +1). Soma 581 min em 10 partidas (8T/2R). com 0 gol(s) verificado(s) por partida. 2 assistência(s) na temporada (2 G+A) e nota média 6.72. Vínculo: contrato até 2027 (Rodízio). avaliado em € 1.100.000.
A21: 245704 | B21: 20 | C21: Martí Vilà | D21: Martí Vilà García | E21: Suplente (Banco) | F21: Titular Efetivo (47% min) | G21: Rodízio | H21: LE | I21: ZAG, ME | J21: Defesa | K21: 67 | L21: 67 | M21: =L21-K21 -> 0 | N21: =K21-66 -> 1 | O21: 26 | P21: 25/05/1999 | Q21: Espanha | R21: 1100000 | S21: 3500 | T21: Sem multa rescisória | U21: 2028 | V21: Seguro (até 2028) | W21: =COUNTIFS('Desempenho por Jogo (Logs)'!$G$5:$G$206, A21) -> 11 | X21: =COUNTIFS('Desempenho por Jogo (Logs)'!$G$5:$G$206, A21, 'Desempenho por Jogo (Logs)'!$J$5:$J$206, "<>RES") -> 7 | Y21: =COUNTIFS('Desempenho por Jogo (Logs)'!$G$5:$G$206, A21, 'Desempenho por Jogo (Logs)'!$J$5:$J$206, "RES") -> 4 | Z21: =SUMIFS('Desempenho por Jogo (Logs)'!$K$5:$K$206, 'Desempenho por Jogo (Logs)'!$G$5:$G$206, A21) -> 555 | AA21: =IF(Z21>0, Z21/540, 0) -> 0.474 | AB21: =SUMIFS('Desempenho por Jogo (Logs)'!$L$5:$L$206, 'Desempenho por Jogo (Logs)'!$G$5:$G$206, A21) -> 0 | AC21: 0 | AD21: =AB21+AC21 -> 0 | AE21: =IF(Z21>0, ROUND((AD21/Z21)*90, 2), 0) -> 0 | AF21: =SUMIFS('Desempenho por Jogo (Logs)'!$L$5:$L$206, 'Desempenho por Jogo (Logs)'!$G$5:$G$206, A21, 'Desempenho por Jogo (Logs)'!$C$5:$C$206, "*Liga*") -> 0 | AG21: 0 | AH21: =SUMIFS('Desempenho por Jogo (Logs)'!$L$5:$L$206, 'Desempenho por Jogo (Logs)'!$G$5:$G$206, A21, 'Desempenho por Jogo (Logs)'!$C$5:$C$206, "*Trophy*") -> 0 | AI21: 0 | AJ21: 0 | AK21: =IFERROR(ROUND(AVERAGEIFS('Desempenho por Jogo (Logs)'!$N$5:$N$206, 'Desempenho por Jogo (Logs)'!$G$5:$G$206, A21, 'Desempenho por Jogo (Logs)'!$N$5:$N$206, ">0"), 2), "S/N") -> 6.39 | AL21: Oscilante (6,34) | AM21: =IF(W21=0, "Nula (0 jogos)", IF(OR(W21<=2, Z21<150), "Baixa — Amostra Insuficiente", IF(AND(W21>=4, Z21>=240), "Alta", "Moderada"))) -> Alta (≥4J e ≥270m) | AN21: =IF(W21=0, "Sem minutagem no save", IF(OR(W21<=2, Z21<150), "Amostra insuficiente (" & W21 & "J / " & Z21 & "m) — Continuar observando", IF(AK21>=7.5, "Promover minutos / Titularidade em ascensão", IF(AK21>=7.0, "Manter minutagem atual", "Avaliar opções / Rotação")))) -> Manter na Rotação do Elenco | AO21: Participação regular na rotação (555 min em 11J, OVR 67) | AP21: Atleta de 26 anos (Espanha). posição LE (ZAG. ME). hierarquia atual 'Suplente (Banco)'. Overall 67 e Potencial 67 (margem de potencial +0; evolução real no save +1). Soma 555 min em 11 partidas (7T/4R). com 0 gol(s) verificado(s) por partida. 0 assistência(s) na temporada (0 G+A) e nota média 6.39. Vínculo: contrato até 2028 (Rodízio). avaliado em € 1.100.000.
A22: 75437 | B22: 29 | C22: Kim Min Su | D22: Min Su Kim | E22: Suplente (Banco) | F22: Titular Efetivo (40% min) | G22: Rodízio | H22: PE | I22: ME | J22: Ataque | K22: 71 | L22: 82 | M22: =L22-K22 -> 11 | N22: =K22-70 -> 1 | O22: 19 | P22: 20/01/2006 | Q22: Coreia do Sul | R22: 4500000 | S22: 4700 | T22: Emprestado (Sem multa) | U22: 2027 | V22: Empréstimo até Jun/2026 | W22: =COUNTIFS('Desempenho por Jogo (Logs)'!$G$5:$G$206, A22) -> 10 | X22: =COUNTIFS('Desempenho por Jogo (Logs)'!$G$5:$G$206, A22, 'Desempenho por Jogo (Logs)'!$J$5:$J$206, "<>RES") -> 7 | Y22: =COUNTIFS('Desempenho por Jogo (Logs)'!$G$5:$G$206, A22, 'Desempenho por Jogo (Logs)'!$J$5:$J$206, "RES") -> 3 | Z22: =SUMIFS('Desempenho por Jogo (Logs)'!$K$5:$K$206, 'Desempenho por Jogo (Logs)'!$G$5:$G$206, A22) -> 462 | AA22: =IF(Z22>0, Z22/540, 0) -> 0.395 | AB22: =SUMIFS('Desempenho por Jogo (Logs)'!$L$5:$L$206, 'Desempenho por Jogo (Logs)'!$G$5:$G$206, A22) -> 1 | AC22: 1 | AD22: =AB22+AC22 -> 2 | AE22: =IF(Z22>0, ROUND((AD22/Z22)*90, 2), 0) -> 0.39 | AF22: =SUMIFS('Desempenho por Jogo (Logs)'!$L$5:$L$206, 'Desempenho por Jogo (Logs)'!$G$5:$G$206, A22, 'Desempenho por Jogo (Logs)'!$C$5:$C$206, "*Liga*") -> 1 | AG22: 1 | AH22: =SUMIFS('Desempenho por Jogo (Logs)'!$L$5:$L$206, 'Desempenho por Jogo (Logs)'!$G$5:$G$206, A22, 'Desempenho por Jogo (Logs)'!$C$5:$C$206, "*Trophy*") -> 0 | AI22: 0 | AJ22: 0 | AK22: =IFERROR(ROUND(AVERAGEIFS('Desempenho por Jogo (Logs)'!$N$5:$N$206, 'Desempenho por Jogo (Logs)'!$G$5:$G$206, A22, 'Desempenho por Jogo (Logs)'!$N$5:$N$206, ">0"), 2), "S/N") -> 6.68 | AL22: Regular (6,58) | AM22: =IF(W22=0, "Nula (0 jogos)", IF(OR(W22<=2, Z22<150), "Baixa — Amostra Insuficiente", IF(AND(W22>=4, Z22>=240), "Alta", "Moderada"))) -> Alta (≥4J e ≥270m) | AN22: =IF(W22=0, "Sem minutagem no save", IF(OR(W22<=2, Z22<150), "Amostra insuficiente (" & W22 & "J / " & Z22 & "m) — Continuar observando", IF(AK22>=7.5, "Promover minutos / Titularidade em ascensão", IF(AK22>=7.0, "Manter minutagem atual", "Avaliar opções / Rotação")))) -> Jovem em Desenvolvimento Ativo — Manter Minutagem | AO22: 19 anos, POT 82 (+11 margem) e 462 min disputados (10J) | AP22: Atleta de 19 anos (Coreia do Sul). posição PE (ME). hierarquia atual 'Suplente (Banco)'. Overall 71 e Potencial 82 (margem de potencial +11; evolução real no save +1). Soma 462 min em 10 partidas (7T/3R). com 1 gol(s) verificado(s) por partida. 1 assistência(s) na temporada (2 G+A) e nota média 6.68. Vínculo: atleta emprestado ao clube até 2026. avaliado em € 4.500.000.
A23: 274828 | B23: 7 | C23: Álex Calvo | D23: Alejandro Calvo Mata | E23: Reserva (Não Relacionado) | F23: Rotação Ativa (24% min) | G23: Rodízio | H23: PD | I23: MD | J23: Ataque | K23: 67 | L23: 72 | M23: =L23-K23 -> 5 | N23: =K23-66 -> 1 | O23: 21 | P23: 21/02/2004 | Q23: Espanha | R23: 1600000 | S23: 2900 | T23: € 2.800.000 | U23: 2028 | V23: Seguro (até 2028) | W23: =COUNTIFS('Desempenho por Jogo (Logs)'!$G$5:$G$206, A23) -> 5 | X23: =COUNTIFS('Desempenho por Jogo (Logs)'!$G$5:$G$206, A23, 'Desempenho por Jogo (Logs)'!$J$5:$J$206, "<>RES") -> 4 | Y23: =COUNTIFS('Desempenho por Jogo (Logs)'!$G$5:$G$206, A23, 'Desempenho por Jogo (Logs)'!$J$5:$J$206, "RES") -> 1 | Z23: =SUMIFS('Desempenho por Jogo (Logs)'!$K$5:$K$206, 'Desempenho por Jogo (Logs)'!$G$5:$G$206, A23) -> 285 | AA23: =IF(Z23>0, Z23/540, 0) -> 0.244 | AB23: =SUMIFS('Desempenho por Jogo (Logs)'!$L$5:$L$206, 'Desempenho por Jogo (Logs)'!$G$5:$G$206, A23) -> 0 | AC23: 1 | AD23: =AB23+AC23 -> 1 | AE23: =IF(Z23>0, ROUND((AD23/Z23)*90, 2), 0) -> 0.32 | AF23: =SUMIFS('Desempenho por Jogo (Logs)'!$L$5:$L$206, 'Desempenho por Jogo (Logs)'!$G$5:$G$206, A23, 'Desempenho por Jogo (Logs)'!$C$5:$C$206, "*Liga*") -> 0 | AG23: 1 | AH23: =SUMIFS('Desempenho por Jogo (Logs)'!$L$5:$L$206, 'Desempenho por Jogo (Logs)'!$G$5:$G$206, A23, 'Desempenho por Jogo (Logs)'!$C$5:$C$206, "*Trophy*") -> 0 | AI23: 0 | AJ23: 0 | AK23: =IFERROR(ROUND(AVERAGEIFS('Desempenho por Jogo (Logs)'!$N$5:$N$206, 'Desempenho por Jogo (Logs)'!$G$5:$G$206, A23, 'Desempenho por Jogo (Logs)'!$N$5:$N$206, ">0"), 2), "S/N") -> 6.66 | AL23: Regular (6,66) | AM23: =IF(W23=0, "Nula (0 jogos)", IF(OR(W23<=2, Z23<150), "Baixa — Amostra Insuficiente", IF(AND(W23>=4, Z23>=240), "Alta", "Moderada"))) -> Alta (≥4J e ≥270m) | AN23: =IF(W23=0, "Sem minutagem no save", IF(OR(W23<=2, Z23<150), "Amostra insuficiente (" & W23 & "J / " & Z23 & "m) — Continuar observando", IF(AK23>=7.5, "Promover minutos / Titularidade em ascensão", IF(AK23>=7.0, "Manter minutagem atual", "Avaliar opções / Rotação")))) -> Manter na Rotação do Elenco | AO23: Participação regular na rotação (285 min em 5J, OVR 67) | AP23: Atleta de 21 anos (Espanha). posição PD (MD). hierarquia atual 'Reserva (Não Relacionado)'. Overall 67 e Potencial 72 (margem de potencial +5; evolução real no save +1). Soma 285 min em 5 partidas (4T/1R). com 0 gol(s) verificado(s) por partida. 1 assistência(s) na temporada (1 G+A) e nota média 6.66. Vínculo: contrato até 2028 (Rodízio). avaliado em € 1.600.000.
A24: 277311 | B24: 10 | C24: Álvaro Martín | D24: Álvaro Martín | E24: Reserva (Não Relacionado) | F24: Rotação Ativa (29% min) | G24: Rodízio | H24: MC | I24: MEI, VOL | J24: Meio-Campo | K24: 63 | L24: 68 | M24: =L24-K24 -> 5 | N24: =K24-63 -> 0 | O24: 24 | P24: 16/01/2001 | Q24: Espanha | R24: 850000 | S24: 2200 | T24: Sem multa rescisória | U24: 2030 | V24: Seguro (até 2030) | W24: =COUNTIFS('Desempenho por Jogo (Logs)'!$G$5:$G$206, A24) -> 5 | X24: =COUNTIFS('Desempenho por Jogo (Logs)'!$G$5:$G$206, A24, 'Desempenho por Jogo (Logs)'!$J$5:$J$206, "<>RES") -> 4 | Y24: =COUNTIFS('Desempenho por Jogo (Logs)'!$G$5:$G$206, A24, 'Desempenho por Jogo (Logs)'!$J$5:$J$206, "RES") -> 1 | Z24: =SUMIFS('Desempenho por Jogo (Logs)'!$K$5:$K$206, 'Desempenho por Jogo (Logs)'!$G$5:$G$206, A24) -> 343 | AA24: =IF(Z24>0, Z24/540, 0) -> 0.293 | AB24: =SUMIFS('Desempenho por Jogo (Logs)'!$L$5:$L$206, 'Desempenho por Jogo (Logs)'!$G$5:$G$206, A24) -> 0 | AC24: 0 | AD24: =AB24+AC24 -> 0 | AE24: =IF(Z24>0, ROUND((AD24/Z24)*90, 2), 0) -> 0 | AF24: =SUMIFS('Desempenho por Jogo (Logs)'!$L$5:$L$206, 'Desempenho por Jogo (Logs)'!$G$5:$G$206, A24, 'Desempenho por Jogo (Logs)'!$C$5:$C$206, "*Liga*") -> 0 | AG24: 0 | AH24: =SUMIFS('Desempenho por Jogo (Logs)'!$L$5:$L$206, 'Desempenho por Jogo (Logs)'!$G$5:$G$206, A24, 'Desempenho por Jogo (Logs)'!$C$5:$C$206, "*Trophy*") -> 0 | AI24: 0 | AJ24: 0 | AK24: =IFERROR(ROUND(AVERAGEIFS('Desempenho por Jogo (Logs)'!$N$5:$N$206, 'Desempenho por Jogo (Logs)'!$G$5:$G$206, A24, 'Desempenho por Jogo (Logs)'!$N$5:$N$206, ">0"), 2), "S/N") -> 6.7 | AL24: Regular (6,70) | AM24: =IF(W24=0, "Nula (0 jogos)", IF(OR(W24<=2, Z24<150), "Baixa — Amostra Insuficiente", IF(AND(W24>=4, Z24>=240), "Alta", "Moderada"))) -> Alta (≥4J e ≥270m) | AN24: =IF(W24=0, "Sem minutagem no save", IF(OR(W24<=2, Z24<150), "Amostra insuficiente (" & W24 & "J / " & Z24 & "m) — Continuar observando", IF(AK24>=7.5, "Promover minutos / Titularidade em ascensão", IF(AK24>=7.0, "Manter minutagem atual", "Avaliar opções / Rotação")))) -> Manter na Rotação do Elenco | AO24: Participação regular na rotação (343 min em 5J, OVR 63) | AP24: Atleta de 24 anos (Espanha). posição MC (MEI. VOL). hierarquia atual 'Reserva (Não Relacionado)'. Overall 63 e Potencial 68 (margem de potencial +5; evolução real no save +0). Soma 343 min em 5 partidas (4T/1R). com 0 gol(s) verificado(s) por partida. 0 assistência(s) na temporada (0 G+A) e nota média 6.70. Vínculo: contrato até 2030 (Rodízio). avaliado em € 850.000.
A25: 260044 | B25: 11 | C25: Lautaro de León | D25: Lautaro de León Billar | E25: Reserva (Não Relacionado) | F25: Titular Efetivo (46% min) | G25: Importante | H25: ATA | I25: — | J25: Ataque | K25: 68 | L25: 72 | M25: =L25-K25 -> 4 | N25: =K25-67 -> 1 | O25: 24 | P25: 10/02/2001 | Q25: Uruguai | R25: 1800000 | S25: 5000 | T25: € 4.000.000 | U25: 2028 | V25: Seguro (até 2028) | W25: =COUNTIFS('Desempenho por Jogo (Logs)'!$G$5:$G$206, A25) -> 7 | X25: =COUNTIFS('Desempenho por Jogo (Logs)'!$G$5:$G$206, A25, 'Desempenho por Jogo (Logs)'!$J$5:$J$206, "<>RES") -> 7 | Y25: =COUNTIFS('Desempenho por Jogo (Logs)'!$G$5:$G$206, A25, 'Desempenho por Jogo (Logs)'!$J$5:$J$206, "RES") -> 0 | Z25: =SUMIFS('Desempenho por Jogo (Logs)'!$K$5:$K$206, 'Desempenho por Jogo (Logs)'!$G$5:$G$206, A25) -> 534 | AA25: =IF(Z25>0, Z25/540, 0) -> 0.456 | AB25: =SUMIFS('Desempenho por Jogo (Logs)'!$L$5:$L$206, 'Desempenho por Jogo (Logs)'!$G$5:$G$206, A25) -> 5 | AC25: 0 | AD25: =AB25+AC25 -> 5 | AE25: =IF(Z25>0, ROUND((AD25/Z25)*90, 2), 0) -> 0.84 | AF25: =SUMIFS('Desempenho por Jogo (Logs)'!$L$5:$L$206, 'Desempenho por Jogo (Logs)'!$G$5:$G$206, A25, 'Desempenho por Jogo (Logs)'!$C$5:$C$206, "*Liga*") -> 2 | AG25: 0 | AH25: =SUMIFS('Desempenho por Jogo (Logs)'!$L$5:$L$206, 'Desempenho por Jogo (Logs)'!$G$5:$G$206, A25, 'Desempenho por Jogo (Logs)'!$C$5:$C$206, "*Trophy*") -> 3 | AI25: 0 | AJ25: 2 | AK25: =IFERROR(ROUND(AVERAGEIFS('Desempenho por Jogo (Logs)'!$N$5:$N$206, 'Desempenho por Jogo (Logs)'!$G$5:$G$206, A25, 'Desempenho por Jogo (Logs)'!$N$5:$N$206, ">0"), 2), "S/N") -> 7.11 | AL25: Regular (6,70) | AM25: =IF(W25=0, "Nula (0 jogos)", IF(OR(W25<=2, Z25<150), "Baixa — Amostra Insuficiente", IF(AND(W25>=4, Z25>=240), "Alta", "Moderada"))) -> Alta (≥4J e ≥270m) | AN25: =IF(W25=0, "Sem minutagem no save", IF(OR(W25<=2, Z25<150), "Amostra insuficiente (" & W25 & "J / " & Z25 & "m) — Continuar observando", IF(AK25>=7.5, "Promover minutos / Titularidade em ascensão", IF(AK25>=7.0, "Manter minutagem atual", "Avaliar opções / Rotação")))) -> Manter na Rotação do Elenco | AO25: Participação regular na rotação (534 min em 7J, OVR 68) | AP25: Atleta de 24 anos (Uruguai). posição ATA. hierarquia atual 'Reserva (Não Relacionado)'. Overall 68 e Potencial 72 (margem de potencial +4; evolução real no save +1). Soma 534 min em 7 partidas (7T/0R). com 5 gol(s) verificado(s) por partida. 0 assistência(s) na temporada (5 G+A) e nota média 7.11. Vínculo: contrato até 2028 (Importante). avaliado em € 1.800.000.
A26: 79752 | B26: 18 | C26: Marc Doménech | D26: Marc Doménech | E26: Reserva (Não Relacionado) | F26: Titular Efetivo (34% min) | G26: Rodízio | H26: MC | I26: VOL | J26: Meio-Campo | K26: 65 | L26: 71 | M26: =L26-K26 -> 6 | N26: =K26-64 -> 1 | O26: 22 | P26: 02/11/2002 | Q26: Espanha | R26: 1400000 | S26: 2400 | T26: Sem multa rescisória | U26: 2028 | V26: Seguro (até 2028) | W26: =COUNTIFS('Desempenho por Jogo (Logs)'!$G$5:$G$206, A26) -> 9 | X26: =COUNTIFS('Desempenho por Jogo (Logs)'!$G$5:$G$206, A26, 'Desempenho por Jogo (Logs)'!$J$5:$J$206, "<>RES") -> 4 | Y26: =COUNTIFS('Desempenho por Jogo (Logs)'!$G$5:$G$206, A26, 'Desempenho por Jogo (Logs)'!$J$5:$J$206, "RES") -> 5 | Z26: =SUMIFS('Desempenho por Jogo (Logs)'!$K$5:$K$206, 'Desempenho por Jogo (Logs)'!$G$5:$G$206, A26) -> 397 | AA26: =IF(Z26>0, Z26/540, 0) -> 0.339 | AB26: =SUMIFS('Desempenho por Jogo (Logs)'!$L$5:$L$206, 'Desempenho por Jogo (Logs)'!$G$5:$G$206, A26) -> 0 | AC26: 0 | AD26: =AB26+AC26 -> 0 | AE26: =IF(Z26>0, ROUND((AD26/Z26)*90, 2), 0) -> 0 | AF26: =SUMIFS('Desempenho por Jogo (Logs)'!$L$5:$L$206, 'Desempenho por Jogo (Logs)'!$G$5:$G$206, A26, 'Desempenho por Jogo (Logs)'!$C$5:$C$206, "*Liga*") -> 0 | AG26: 0 | AH26: =SUMIFS('Desempenho por Jogo (Logs)'!$L$5:$L$206, 'Desempenho por Jogo (Logs)'!$G$5:$G$206, A26, 'Desempenho por Jogo (Logs)'!$C$5:$C$206, "*Trophy*") -> 0 | AI26: 0 | AJ26: 1 | AK26: =IFERROR(ROUND(AVERAGEIFS('Desempenho por Jogo (Logs)'!$N$5:$N$206, 'Desempenho por Jogo (Logs)'!$G$5:$G$206, A26, 'Desempenho por Jogo (Logs)'!$N$5:$N$206, ">0"), 2), "S/N") -> 6.73 | AL26: Oscilante (6,42) | AM26: =IF(W26=0, "Nula (0 jogos)", IF(OR(W26<=2, Z26<150), "Baixa — Amostra Insuficiente", IF(AND(W26>=4, Z26>=240), "Alta", "Moderada"))) -> Alta (≥4J e ≥270m) | AN26: =IF(W26=0, "Sem minutagem no save", IF(OR(W26<=2, Z26<150), "Amostra insuficiente (" & W26 & "J / " & Z26 & "m) — Continuar observando", IF(AK26>=7.5, "Promover minutos / Titularidade em ascensão", IF(AK26>=7.0, "Manter minutagem atual", "Avaliar opções / Rotação")))) -> Manter na Rotação do Elenco | AO26: Participação regular na rotação (397 min em 9J, OVR 65) | AP26: Atleta de 22 anos (Espanha). posição MC (VOL). hierarquia atual 'Reserva (Não Relacionado)'. Overall 65 e Potencial 71 (margem de potencial +6; evolução real no save +1). Soma 397 min em 9 partidas (4T/5R). com 0 gol(s) verificado(s) por partida. 0 assistência(s) na temporada (0 G+A) e nota média 6.73. Vínculo: contrato até 2028 (Rodízio). avaliado em € 1.400.000.
A27: 228707 | B27: 23 | C27: Diego Alende | D27: Diego Alende López | E27: Reserva (Não Relacionado) | F27: Titular Efetivo (31% min) | G27: Rodízio | H27: ZAG | I27: — | J27: Defesa | K27: 67 | L27: 68 | M27: =L27-K27 -> 1 | N27: =K27-66 -> 1 | O27: 28 | P27: 26/08/1997 | Q27: Espanha | R27: 1100000 | S27: 3500 | T27: € 1.800.000 | U27: 2027 | V27: Atenção: Expira em 2027 (2 anos) | W27: =COUNTIFS('Desempenho por Jogo (Logs)'!$G$5:$G$206, A27) -> 4 | X27: =COUNTIFS('Desempenho por Jogo (Logs)'!$G$5:$G$206, A27, 'Desempenho por Jogo (Logs)'!$J$5:$J$206, "<>RES") -> 4 | Y27: =COUNTIFS('Desempenho por Jogo (Logs)'!$G$5:$G$206, A27, 'Desempenho por Jogo (Logs)'!$J$5:$J$206, "RES") -> 0 | Z27: =SUMIFS('Desempenho por Jogo (Logs)'!$K$5:$K$206, 'Desempenho por Jogo (Logs)'!$G$5:$G$206, A27) -> 360 | AA27: =IF(Z27>0, Z27/540, 0) -> 0.308 | AB27: =SUMIFS('Desempenho por Jogo (Logs)'!$L$5:$L$206, 'Desempenho por Jogo (Logs)'!$G$5:$G$206, A27) -> 0 | AC27: 0 | AD27: =AB27+AC27 -> 0 | AE27: =IF(Z27>0, ROUND((AD27/Z27)*90, 2), 0) -> 0 | AF27: =SUMIFS('Desempenho por Jogo (Logs)'!$L$5:$L$206, 'Desempenho por Jogo (Logs)'!$G$5:$G$206, A27, 'Desempenho por Jogo (Logs)'!$C$5:$C$206, "*Liga*") -> 0 | AG27: 0 | AH27: =SUMIFS('Desempenho por Jogo (Logs)'!$L$5:$L$206, 'Desempenho por Jogo (Logs)'!$G$5:$G$206, A27, 'Desempenho por Jogo (Logs)'!$C$5:$C$206, "*Trophy*") -> 0 | AI27: 0 | AJ27: 0 | AK27: =IFERROR(ROUND(AVERAGEIFS('Desempenho por Jogo (Logs)'!$N$5:$N$206, 'Desempenho por Jogo (Logs)'!$G$5:$G$206, A27, 'Desempenho por Jogo (Logs)'!$N$5:$N$206, ">0"), 2), "S/N") -> 7.3 | AL27: Boa (7,30) | AM27: =IF(W27=0, "Nula (0 jogos)", IF(OR(W27<=2, Z27<150), "Baixa — Amostra Insuficiente", IF(AND(W27>=4, Z27>=240), "Alta", "Moderada"))) -> Alta (≥4J e ≥270m) | AN27: =IF(W27=0, "Sem minutagem no save", IF(OR(W27<=2, Z27<150), "Amostra insuficiente (" & W27 & "J / " & Z27 & "m) — Continuar observando", IF(AK27>=7.5, "Promover minutos / Titularidade em ascensão", IF(AK27>=7.0, "Manter minutagem atual", "Avaliar opções / Rotação")))) -> Sugestão: Testar com Mais Minutos na Rotação | AO27: Suplente com boa produção em 4J / 360 min (Nota 7,30, 0 G+A); sugestão consultiva sem alterar escalação | AP27: Atleta de 28 anos (Espanha). posição ZAG. hierarquia atual 'Reserva (Não Relacionado)'. Overall 67 e Potencial 68 (margem de potencial +1; evolução real no save +1). Soma 360 min em 4 partidas (4T/0R). com 0 gol(s) verificado(s) por partida. 0 assistência(s) na temporada (0 G+A) e nota média 7.30. Vínculo: contrato até 2027 (Rodízio). avaliado em € 1.100.000.
A28: 263347 | B28: 24 | C28: Théo Le Normand | D28: Théo Le Normand | E28: Reserva (Não Relacionado) | F28: Suplente Acionado (14% min) | G28: Rodízio | H28: MEI | I28: MC | J28: Meio-Campo | K28: 63 | L28: 66 | M28: =L28-K28 -> 3 | N28: =K28-63 -> 0 | O28: 25 | P28: 09/08/2000 | Q28: França | R28: 775000 | S28: 2200 | T28: Sem multa rescisória | U28: 2029 | V28: Seguro (até 2029) | W28: =COUNTIFS('Desempenho por Jogo (Logs)'!$G$5:$G$206, A28) -> 3 | X28: =COUNTIFS('Desempenho por Jogo (Logs)'!$G$5:$G$206, A28, 'Desempenho por Jogo (Logs)'!$J$5:$J$206, "<>RES") -> 3 | Y28: =COUNTIFS('Desempenho por Jogo (Logs)'!$G$5:$G$206, A28, 'Desempenho por Jogo (Logs)'!$J$5:$J$206, "RES") -> 0 | Z28: =SUMIFS('Desempenho por Jogo (Logs)'!$K$5:$K$206, 'Desempenho por Jogo (Logs)'!$G$5:$G$206, A28) -> 168 | AA28: =IF(Z28>0, Z28/540, 0) -> 0.144 | AB28: =SUMIFS('Desempenho por Jogo (Logs)'!$L$5:$L$206, 'Desempenho por Jogo (Logs)'!$G$5:$G$206, A28) -> 0 | AC28: 1 | AD28: =AB28+AC28 -> 1 | AE28: =IF(Z28>0, ROUND((AD28/Z28)*90, 2), 0) -> 0.54 | AF28: =SUMIFS('Desempenho por Jogo (Logs)'!$L$5:$L$206, 'Desempenho por Jogo (Logs)'!$G$5:$G$206, A28, 'Desempenho por Jogo (Logs)'!$C$5:$C$206, "*Liga*") -> 0 | AG28: 1 | AH28: =SUMIFS('Desempenho por Jogo (Logs)'!$L$5:$L$206, 'Desempenho por Jogo (Logs)'!$G$5:$G$206, A28, 'Desempenho por Jogo (Logs)'!$C$5:$C$206, "*Trophy*") -> 0 | AI28: 0 | AJ28: 0 | AK28: =IFERROR(ROUND(AVERAGEIFS('Desempenho por Jogo (Logs)'!$N$5:$N$206, 'Desempenho por Jogo (Logs)'!$G$5:$G$206, A28, 'Desempenho por Jogo (Logs)'!$N$5:$N$206, ">0"), 2), "S/N") -> 7.1 | AL28: Boa (7,10) | AM28: =IF(W28=0, "Nula (0 jogos)", IF(OR(W28<=2, Z28<150), "Baixa — Amostra Insuficiente", IF(AND(W28>=4, Z28>=240), "Alta", "Moderada"))) -> Moderada (≥3J e ≥150m) | AN28: =IF(W28=0, "Sem minutagem no save", IF(OR(W28<=2, Z28<150), "Amostra insuficiente (" & W28 & "J / " & Z28 & "m) — Continuar observando", IF(AK28>=7.5, "Promover minutos / Titularidade em ascensão", IF(AK28>=7.0, "Manter minutagem atual", "Avaliar opções / Rotação")))) -> Manter na Rotação do Elenco | AO28: Participação regular na rotação (168 min em 3J, OVR 63) | AP28: Atleta de 25 anos (França). posição MEI (MC). hierarquia atual 'Reserva (Não Relacionado)'. Overall 63 e Potencial 66 (margem de potencial +3; evolução real no save +0). Soma 168 min em 3 partidas (3T/0R). com 0 gol(s) verificado(s) por partida. 1 assistência(s) na temporada (1 G+A) e nota média 7.10. Vínculo: contrato até 2029 (Rodízio). avaliado em € 775.000.
A29: 85904 | B29: 30 | C29: Valle Gómez | D29: Valle Gómez | E29: Reserva (Não Relacionado) | F29: Rotação Ativa (18% min) | G29: Rodízio | H29: MC | I29: VOL | J29: Meio-Campo | K29: 58 | L29: 69 | M29: =L29-K29 -> 11 | N29: =K29-58 -> 0 | O29: 20 | P29: 24/05/2005 | Q29: Espanha | R29: 525000 | S29: 1200 | T29: € 920.000 | U29: 2026 | V29: ⚠️ Crítico: Expira em 2026 (<1 ano) | W29: =COUNTIFS('Desempenho por Jogo (Logs)'!$G$5:$G$206, A29) -> 3 | X29: =COUNTIFS('Desempenho por Jogo (Logs)'!$G$5:$G$206, A29, 'Desempenho por Jogo (Logs)'!$J$5:$J$206, "<>RES") -> 3 | Y29: =COUNTIFS('Desempenho por Jogo (Logs)'!$G$5:$G$206, A29, 'Desempenho por Jogo (Logs)'!$J$5:$J$206, "RES") -> 0 | Z29: =SUMIFS('Desempenho por Jogo (Logs)'!$K$5:$K$206, 'Desempenho por Jogo (Logs)'!$G$5:$G$206, A29) -> 211 | AA29: =IF(Z29>0, Z29/540, 0) -> 0.18 | AB29: =SUMIFS('Desempenho por Jogo (Logs)'!$L$5:$L$206, 'Desempenho por Jogo (Logs)'!$G$5:$G$206, A29) -> 0 | AC29: 1 | AD29: =AB29+AC29 -> 1 | AE29: =IF(Z29>0, ROUND((AD29/Z29)*90, 2), 0) -> 0.43 | AF29: =SUMIFS('Desempenho por Jogo (Logs)'!$L$5:$L$206, 'Desempenho por Jogo (Logs)'!$G$5:$G$206, A29, 'Desempenho por Jogo (Logs)'!$C$5:$C$206, "*Liga*") -> 0 | AG29: 0 | AH29: =SUMIFS('Desempenho por Jogo (Logs)'!$L$5:$L$206, 'Desempenho por Jogo (Logs)'!$G$5:$G$206, A29, 'Desempenho por Jogo (Logs)'!$C$5:$C$206, "*Trophy*") -> 0 | AI29: 1 | AJ29: 0 | AK29: =IFERROR(ROUND(AVERAGEIFS('Desempenho por Jogo (Logs)'!$N$5:$N$206, 'Desempenho por Jogo (Logs)'!$G$5:$G$206, A29, 'Desempenho por Jogo (Logs)'!$N$5:$N$206, ">0"), 2), "S/N") -> 7.4 | AL29: Boa (7,40) | AM29: =IF(W29=0, "Nula (0 jogos)", IF(OR(W29<=2, Z29<150), "Baixa — Amostra Insuficiente", IF(AND(W29>=4, Z29>=240), "Alta", "Moderada"))) -> Moderada (≥3J e ≥150m) | AN29: =IF(W29=0, "Sem minutagem no save", IF(OR(W29<=2, Z29<150), "Amostra insuficiente (" & W29 & "J / " & Z29 & "m) — Continuar observando", IF(AK29>=7.5, "Promover minutos / Titularidade em ascensão", IF(AK29>=7.0, "Manter minutagem atual", "Avaliar opções / Rotação")))) -> Sugestão: Testar com Mais Minutos na Rotação | AO29: Suplente com boa produção em 3J / 211 min (Nota 7,40, 1 G+A); sugestão consultiva sem alterar escalação | AP29: Atleta de 20 anos (Espanha). posição MC (VOL). hierarquia atual 'Reserva (Não Relacionado)'. Overall 58 e Potencial 69 (margem de potencial +11; evolução real no save +0). Soma 211 min em 3 partidas (3T/0R). com 0 gol(s) verificado(s) por partida. 1 assistência(s) na temporada (1 G+A) e nota média 7.40. Vínculo: contrato até 2026 (Rodízio). avaliado em € 525.000.

Sheet Desempenho por Jogo (Logs)
A1: REGISTROS INDIVIDUAIS POR PARTIDA (FONTE PRIMÁRIA DO SISTEMA) — FC ANDORRA
A2: Total: 202 atuações em 13 jogos | Soma de Gols nos Logs: 32 gols | Assistências por Partida: valor exato ou 'N/D' quando o binário guarda apenas o acumulado da competição
A4: Jogo # | B4: Data | C4: Competição | D4: Adversário | E4: Mando | F4: Placar | G4: ID Atleta | H4: Nº | I4: Jogador | J4: Posição Exercida | K4: Minutos | L4: Gols na Partida | M4: Assistências na Partida | N4: Nota Oficial
A5: #1 | B5: 18/07/2025 | C5: Torneio de Pré-Temporada (Champions Trophy) | D5: Fortuna Sittard | E5: Casa | F5: 1 x 1 | G5: 241505 | H5: 17 | I5: Thomas Carrique | J5: LD | K5: 90 | L5: 0 | M5: 0 | N5: 6.9
A6: #1 | B6: 18/07/2025 | C6: Torneio de Pré-Temporada (Champions Trophy) | D6: Fortuna Sittard | E6: Casa | F6: 1 x 1 | G6: 279881 | H6: 21 | I6: Efe Akman | J6: MC | K6: 90 | L6: 0 | M6: N/D | N6: 6.7
A7: #1 | B7: 18/07/2025 | C7: Torneio de Pré-Temporada (Champions Trophy) | D7: Fortuna Sittard | E7: Casa | F7: 1 x 1 | G7: 271955 | H7: 5 | I7: Bomba | J7: ZAG | K7: 90 | L7: 0 | M7: 0 | N7: 6.3
A8: #1 | B8: 18/07/2025 | C8: Torneio de Pré-Temporada (Champions Trophy) | D8: Fortuna Sittard | E8: Casa | F8: 1 x 1 | G8: 276198 | H8: 25 | I8: Áron Yaakobishvili | J8: GOL | K8: 90 | L8: 0 | M8: 0 | N8: 6.1
A9: #1 | B9: 18/07/2025 | C9: Torneio de Pré-Temporada (Champions Trophy) | D9: Fortuna Sittard | E9: Casa | F9: 1 x 1 | G9: 266100 | H9: 6 | I9: Daniel Villahermosa | J9: MC | K9: 88 | L9: 0 | M9: N/D | N9: 7.9
A10: #1 | B10: 18/07/2025 | C10: Torneio de Pré-Temporada (Champions Trophy) | D10: Fortuna Sittard | E10: Casa | F10: 1 x 1 | G10: 260044 | H10: 11 | I10: Lautaro de León | J10: ATA | K10: 88 | L10: 1 | M10: 0 | N10: 7.3
A11: #1 | B11: 18/07/2025 | C11: Torneio de Pré-Temporada (Champions Trophy) | D11: Fortuna Sittard | E11: Casa | F11: 1 x 1 | G11: 75437 | H11: 29 | I11: Kim Min Su | J11: PE | K11: 88 | L11: 0 | M11: 0 | N11: 6.7
A12: #1 | B12: 18/07/2025 | C12: Torneio de Pré-Temporada (Champions Trophy) | D12: Fortuna Sittard | E12: Casa | F12: 1 x 1 | G12: 277311 | H12: 10 | I12: Álvaro Martín | J12: MC | K12: 88 | L12: 0 | M12: 0 | N12: 6.2
A13: #1 | B13: 18/07/2025 | C13: Torneio de Pré-Temporada (Champions Trophy) | D13: Fortuna Sittard | E13: Casa | F13: 1 x 1 | G13: 279603 | H13: 15 | I13: Aingeru Olabarrieta | J13: PD | K13: 88 | L13: 0 | M13: N/D | N13: 6.1
A14: #1 | B14: 18/07/2025 | C14: Torneio de Pré-Temporada (Champions Trophy) | D14: Fortuna Sittard | E14: Casa | F14: 1 x 1 | G14: 245704 | H14: 20 | I14: Martí Vilà | J14: LE (SUB) | K14: 46 | L14: 0 | M14: 0 | N14: 6.1
A15: #1 | B15: 18/07/2025 | C15: Torneio de Pré-Temporada (Champions Trophy) | D15: Fortuna Sittard | E15: Casa | F15: 1 x 1 | G15: 79703 | H15: 4 | I15: Gaël Alonso | J15: ZAG (SUB) | K15: 46 | L15: 0 | M15: 0 | N15: 4.8
A16: #1 | B16: 18/07/2025 | C16: Torneio de Pré-Temporada (Champions Trophy) | D16: Fortuna Sittard | E16: Casa | F16: 1 x 1 | G16: 263006 | H16: 19 | I16: Imanol | J16: LE | K16: 45 | L16: 0 | M16: 0 | N16: 7.5
A17: #1 | B17: 18/07/2025 | C17: Torneio de Pré-Temporada (Champions Trophy) | D17: Fortuna Sittard | E17: Casa | F17: 1 x 1 | G17: 247500 | H17: 12 | I17: Edgar González | J17: ZAG | K17: 45 | L17: 0 | M17: 0 | N17: 6.7
A18: #1 | B18: 18/07/2025 | C18: Torneio de Pré-Temporada (Champions Trophy) | D18: Fortuna Sittard | E18: Casa | F18: 1 x 1 | G18: 262498 | H18: 2 | I18: Álex Petxa | J18: LD (SUB) | K18: 3 | L18: 0 | M18: 0 | N18: 6.5
A19: #1 | B19: 18/07/2025 | C19: Torneio de Pré-Temporada (Champions Trophy) | D19: Fortuna Sittard | E19: Casa | F19: 1 x 1 | G19: 79752 | H19: 18 | I19: Marc Doménech | J19: MC (SUB) | K19: 3 | L19: 0 | M19: 0 | N19: 6.4
A20: #1 | B20: 18/07/2025 | C20: Torneio de Pré-Temporada (Champions Trophy) | D20: Fortuna Sittard | E20: Casa | F20: 1 x 1 | G20: 278758 | H20: 16 | I20: Jastin | J20: ME (SUB) | K20: 3 | L20: 0 | M20: 0 | N20: 6.2
A21: #1 | B21: 18/07/2025 | C21: Torneio de Pré-Temporada (Champions Trophy) | D21: Fortuna Sittard | E21: Casa | F21: 1 x 1 | G21: 274828 | H21: 7 | I21: Álex Calvo | J21: PD (SUB) | K21: 3 | L21: 0 | M21: 0 | N21: 6.2
A22: #2 | B22: 22/07/2025 | C22: Torneio de Pré-Temporada (Champions Trophy) | D22: Aberdeen | E22: Fora | F22: 0 x 2 | G22: 79752 | H22: 18 | I22: Marc Doménech | J22: MC | K22: 90 | L22: 0 | M22: 0 | N22: 9.1
A23: #2 | B23: 22/07/2025 | C23: Torneio de Pré-Temporada (Champions Trophy) | D23: Aberdeen | E23: Fora | F23: 0 x 2 | G23: 271955 | H23: 5 | I23: Bomba | J23: ZAG | K23: 90 | L23: 0 | M23: 0 | N23: 8.8
A24: #2 | B24: 22/07/2025 | C24: Torneio de Pré-Temporada (Champions Trophy) | D24: Aberdeen | E24: Fora | F24: 0 x 2 | G24: 273022 | H24: 3 | I24: Yeray Cabanzón | J24: MD | K24: 90 | L24: 1 | M24: 0 | N24: 8.8
A25: #2 | B25: 22/07/2025 | C25: Torneio de Pré-Temporada (Champions Trophy) | D25: Aberdeen | E25: Fora | F25: 0 x 2 | G25: 236393 | H25: 22 | I25: Marc Cardona | J25: ATA | K25: 90 | L25: 0 | M25: 1 | N25: 8.7
... A28: #2 | B28: 22/07/2025 | C28: Torneio de Pré-Temporada (Champions Trophy) | D28: Aberdeen | E28: Fora | F28: 0 x 2 | G28: 263006 | H28: 19 | I28: Imanol | J28: LE | K28: 90 | L28: 1 | M28: 0 | N28: 8.4
A29: #2 | B29: 22/07/2025 | C29: Torneio de Pré-Temporada (Champions Trophy) | D29: Aberdeen | E29: Fora | F29: 0 x 2 | G29: 85904 | H29: 30 | I29: Valle Gómez | J29: MC | K29: 90 | L29: 0 | M29: N/D | N29: 8.1
A30: #2 | B30: 22/07/2025 | C30: Torneio de Pré-Temporada (Champions Trophy) | D30: Aberdeen | E30: Fora | F30: 0 x 2 | G30: 265405 | H30: 13 | I30: Jesús Owono | J30: GOL | K30: 90 | L30: 0 | M30: 0 | N30: 7.4
A31: #2 | B31: 22/07/2025 | C31: Torneio de Pré-Temporada (Champions Trophy) | D31: Aberdeen | E31: Fora | F31: 0 x 2 | G31: 278758 | H31: 16 | I31: Jastin | J31: ME | K31: 90 | L31: 0 | M31: 0 | N31: 6.5
A32: #2 | B32: 22/07/2025 | C32: Torneio de Pré-Temporada (Champions Trophy) | D32: Aberdeen | E32: Fora | F32: 0 x 2 | G32: 247500 | H32: 12 | I32: Edgar González | J32: ZAG | K32: 75 | L32: 0 | M32: 0 | N32: 6.1
A33: #2 | B33: 22/07/2025 | C33: Torneio de Pré-Temporada (Champions Trophy) | D33: Aberdeen | E33: Fora | F33: 0 x 2 | G33: 79703 | H33: 4 | I33: Gaël Alonso | J33: ZAG (SUB) | K33: 15 | L33: 0 | M33: 0 | N33: 6.1
A34: #3 | B34: 26/07/2025 | C34: Torneio de Pré-Temporada (Champions Trophy) | D34: Estrela da Amadora | E34: Casa | F34: 3 x 0 | G34: 260044 | H34: 11 | I34: Lautaro de León | J34: ATA | K34: 90 | L34: 2 | M34: 0 | N34: 9
A35: #3 | B35: 26/07/2025 | C35: Torneio de Pré-Temporada (Champions Trophy) | D35: Estrela da Amadora | E35: Casa | F35: 3 x 0 | G35: 276198 | H35: 25 | I35: Áron Yaakobishvili | J35: GOL | K35: 90 | L35: 0 | M35: 0 | N35: 7.6
A36: #3 | B36: 26/07/2025 | C36: Torneio de Pré-Temporada (Champions Trophy) | D36: Estrela da Amadora | E36: Casa | F36: 3 x 0 | G36: 266100 | H36: 6 | I36: Daniel Villahermosa | J36: MC | K36: 90 | L36: 1 | M36: N/D | N36: 7.4
A37: #3 | B37: 26/07/2025 | C37: Torneio de Pré-Temporada (Champions Trophy) | D37: Estrela da Amadora | E37: Casa | F37: 3 x 0 | G37: 247500 | H37: 12 | I37: Edgar González | J37: ZAG | K37: 90 | L37: 0 | M37: 0 | N37: 6.4
A38: #3 | B38: 26/07/2025 | C38: Torneio de Pré-Temporada (Champions Trophy) | D38: Estrela da Amadora | E38: Casa | F38: 3 x 0 | G38: 279881 | H38: 21 | I38: Efe Akman | J38: MC | K38: 45 | L38: 0 | M38: N/D | N38: 8.7
A39: #3 | B39: 26/07/2025 | C39: Torneio de Pré-Temporada (Champions Trophy) | D39: Estrela da Amadora | E39: Casa | F39: 3 x 0 | G39: 279603 | H39: 15 | I39: Aingeru Olabarrieta | J39: PD | K39: 45 | L39: 0 | M39: N/D | N39: 8.2
A40: #3 | B40: 26/07/2025 | C40: Torneio de Pré-Temporada (Champions Trophy) | D40: Estrela da Amadora | E40: Casa | F40: 3 x 0 | G40: 85904 | H40: 30 | I40: Valle Gómez | J40: MC (SUB) | K40: 45 | L40: 0 | M40: N/D | N40: 7.5
A41: #3 | B41: 26/07/2025 | C41: Torneio de Pré-Temporada (Champions Trophy) | D41: Estrela da Amadora | E41: Casa | F41: 3 x 0 | G41: 263347 | H41: 24 | I41: Théo Le Normand | J41: MEI (SUB) | K41: 45 | L41: 0 | M41: 0 | N41: 7.3
A42: #3 | B42: 26/07/2025 | C42: Torneio de Pré-Temporada (Champions Trophy) | D42: Estrela da Amadora | E42: Casa | F42: 3 x 0 | G42: 75437 | H42: 29 | I42: Kim Min Su | J42: PE | K42: 45 | L42: 0 | M42: 0 | N42: 7.2
A43: #3 | B43: 26/07/2025 | C43: Torneio de Pré-Temporada (Champions Trophy) | D43: Estrela da Amadora | E43: Casa | F43: 3 x 0 | G43: 277311 | H43: 10 | I43: Álvaro Martín | J43: MC | K43: 45 | L43: 0 | M43: 0 | N43: 7.1
A44: #3 | B44: 26/07/2025 | C44: Torneio de Pré-Temporada (Champions Trophy) | D44: Estrela da Amadora | E44: Casa | F44: 3 x 0 | G44: 241505 | H44: 17 | I44: Thomas Carrique | J44: LD | K44: 45 | L44: 0 | M44: 0 | N44: 6.8
A45: #3 | B45: 26/07/2025 | C45: Torneio de Pré-Temporada (Champions Trophy) | D45: Estrela da Amadora | E45: Casa | F45: 3 x 0 | G45: 263006 | H45: 19 | I45: Imanol | J45: LE | K45: 45 | L45: 0 | M45: 0 | N45: 6.8
A46: #3 | B46: 26/07/2025 | C46: Torneio de Pré-Temporada (Champions Trophy) | D46: Estrela da Amadora | E46: Casa | F46: 3 x 0 | G46: 262498 | H46: 2 | I46: Álex Petxa | J46: LD (SUB) | K46: 45 | L46: 0 | M46: 0 | N46: 6.8
A47: #3 | B47: 26/07/2025 | C47: Torneio de Pré-Temporada (Champions Trophy) | D47: Estrela da Amadora | E47: Casa | F47: 3 x 0 | G47: 79703 | H47: 4 | I47: Gaël Alonso | J47: ZAG (SUB) | K47: 45 | L47: 0 | M47: 0 | N47: 6.5
A48: #3 | B48: 26/07/2025 | C48: Torneio de Pré-Temporada (Champions Trophy) | D48: Estrela da Amadora | E48: Casa | F48: 3 x 0 | G48: 245704 | H48: 20 | I48: Martí Vilà | J48: LE (SUB) | K48: 45 | L48: 0 | M48: 0 | N48: 6.5
A49: #3 | B49: 26/07/2025 | C49: Torneio de Pré-Temporada (Champions Trophy) | D49: Estrela da Amadora | E49: Casa | F49: 3 x 0 | G49: 271955 | H49: 5 | I49: Bomba | J49: ZAG | K49: 45 | L49: 0 | M49: 0 | N49: 6.1
A50: #3 | B50: 26/07/2025 | C50: Torneio de Pré-Temporada (Champions Trophy) | D50: Estrela da Amadora | E50: Casa | F50: 3 x 0 | G50: 274828 | H50: 7 | I50: Álex Calvo | J50: PD (SUB) | K50: 45 | L50: 0 | M50: 0 | N50: 6.1
A51: #3 | B51: 26/07/2025 | C51: Torneio de Pré-Temporada (Champions Trophy) | D51: Estrela da Amadora | E51: Casa | F51: 3 x 0 | G51: 273022 | H51: 3 | I51: Yeray Cabanzón | J51: MD (SUB) | K51: 45 | L51: 0 | M51: 0 | N51: 5.8
A52: #4 | B52: 17/08/2025 | C52: LaLiga Hypermotion | D52: UD Las Palmas | E52: Fora | F52: 0 x 2 | G52: 276198 | H52: 25 | I52: Áron Yaakobishvili | J52: GOL | K52: 90 | L52: 0 | M52: N/D | N52: 8
A53: #4 | B53: 17/08/2025 | C53: LaLiga Hypermotion | D53: UD Las Palmas | E53: Fora | F53: 0 x 2 | G53: 271955 | H53: 5 | I53: Bomba | J53: ZAG | K53: 90 | L53: 0 | M53: N/D | N53: 7
A54: #4 | B54: 17/08/2025 | C54: LaLiga Hypermotion | D54: UD Las Palmas | E54: Fora | F54: 0 x 2 | G54: 263006 | H54: 19 | I54: Imanol | J54: LE | K54: 90 | L54: 0 | M54: N/D | N54: 7
A55: #4 | B55: 17/08/2025 | C55: LaLiga Hypermotion | D55: UD Las Palmas | E55: Fora | F55: 0 x 2 | G55: 266100 | H55: 6 | I55: Daniel Villahermosa | J55: MC | K55: 90 | L55: 0 | M55: N/D | N55: 7
A56: #4 | B56: 17/08/2025 | C56: LaLiga Hypermotion | D56: UD Las Palmas | E56: Fora | F56: 0 x 2 | G56: 247500 | H56: 12 | I56: Edgar González | J56: ZAG | K56: 90 | L56: 0 | M56: N/D | N56: 7
A57: #4 | B57: 17/08/2025 | C57: LaLiga Hypermotion | D57: UD Las Palmas | E57: Fora | F57: 0 x 2 | G57: 245704 | H57: 20 | I57: Martí Vilà | J57: LE | K57: 90 | L57: 0 | M57: N/D | N57: 6
A58: #4 | B58: 17/08/2025 | C58: LaLiga Hypermotion | D58: UD Las Palmas | E58: Fora | F58: 0 x 2 | G58: 279881 | H58: 21 | I58: Efe Akman | J58: MC | K58: 60 | L58: 0 | M58: N/D | N58: 10
A59: #4 | B59: 17/08/2025 | C59: LaLiga Hypermotion | D59: UD Las Palmas | E59: Fora | F59: 0 x 2 | G59: 75437 | H59: 29 | I59: Kim Min Su | J59: PE | K59: 60 | L59: 1 | M59: N/D | N59: 7
A60: #4 | B60: 17/08/2025 | C60: LaLiga Hypermotion | D60: UD Las Palmas | E60: Fora | F60: 0 x 2 | G60: 275520 | H60: 8 | I60: Manu Bueno | J60: MC | K60: 60 | L60: 0 | M60: N/D | N60: 6
A61: #4 | B61: 17/08/2025 | C61: LaLiga Hypermotion | D61: UD Las Palmas | E61: Fora | F61: 0 x 2 | G61: 260044 | H61: 11 | I61: Lautaro de León | J61: ATA | K61: 60 | L61: 0 | M61: N/D | N61: 6
A62: #4 | B62: 17/08/2025 | C62: LaLiga Hypermotion | D62: UD Las Palmas | E62: Fora | F62: 0 x 2 | G62: 263347 | H62: 24 | I62: Théo Le Normand | J62: MEI | K62: 60 | L62: 0 | M62: N/D | N62: 6
A63: #4 | B63: 17/08/2025 | C63: LaLiga Hypermotion | D63: UD Las Palmas | E63: Fora | F63: 0 x 2 | G63: 273022 | H63: 3 | I63: Yeray Cabanzón | J63: MD (SUB) | K63: 30 | L63: 0 | M63: N/D | N63: 8
... A158: #10 | B158: 27/09/2025 | C158: LaLiga Hypermotion | D158: Racing de Santander | E158: Fora | F158: 0 x 5 | G158: 245704 | H158: 20 | I158: Martí Vilà | J158: LE (SUB) | K158: 14 | L158: 0 | M158: N/D | N158: 6
A159: #11 | B159: 04/10/2025 | C159: LaLiga Hypermotion | D159: CD Leganés | E159: Casa | F159: 1 x 1 | G159: 236393 | H159: 22 | I159: Marc Cardona | J159: ATA | K159: 90 | L159: 1 | M159: 0 | N159: 7.7
A160: #11 | B160: 04/10/2025 | C160: LaLiga Hypermotion | D160: CD Leganés | E160: Casa | F160: 1 x 1 | G160: 241505 | H160: 17 | I160: Thomas Carrique | J160: LD | K160: 90 | L160: 0 | M160: N/D | N160: 7.2
A161: #11 | B161: 04/10/2025 | C161: LaLiga Hypermotion | D161: CD Leganés | E161: Casa | F161: 1 x 1 | G161: 228707 | H161: 23 | I161: Diego Alende | J161: ZAG | K161: 90 | L161: 0 | M161: 0 | N161: 6.7
A162: #11 | B162: 04/10/2025 | C162: LaLiga Hypermotion | D162: CD Leganés | E162: Casa | F162: 1 x 1 | G162: 79703 | H162: 4 | I162: Gaël Alonso | J162: ZAG | K162: 90 | L162: 0 | M162: 0 | N162: 6.3
A163: #11 | B163: 04/10/2025 | C163: LaLiga Hypermotion | D163: CD Leganés | E163: Casa | F163: 1 x 1 | G163: 265405 | H163: 13 | I163: Jesús Owono | J163: GOL | K163: 90 | L163: 0 | M163: 0 | N163: 6
A164: #11 | B164: 04/10/2025 | C164: LaLiga Hypermotion | D164: CD Leganés | E164: Casa | F164: 1 x 1 | G164: 245704 | H164: 20 | I164: Martí Vilà | J164: LE | K164: 90 | L164: 0 | M164: 0 | N164: 6
A165: #11 | B165: 04/10/2025 | C165: LaLiga Hypermotion | D165: CD Leganés | E165: Casa | F165: 1 x 1 | G165: 274828 | H165: 7 | I165: Álex Calvo | J165: PD | K165: 76 | L165: 0 | M165: N/D | N165: 7.5
A166: #11 | B166: 04/10/2025 | C166: LaLiga Hypermotion | D166: CD Leganés | E166: Casa | F166: 1 x 1 | G166: 278758 | H166: 16 | I166: Jastin | J166: PE | K166: 76 | L166: 0 | M166: N/D | N166: 7
A167: #11 | B167: 04/10/2025 | C167: LaLiga Hypermotion | D167: CD Leganés | E167: Casa | F167: 1 x 1 | G167: 79752 | H167: 18 | I167: Marc Doménech | J167: MC | K167: 76 | L167: 0 | M167: 0 | N167: 6.9
A168: #11 | B168: 04/10/2025 | C168: LaLiga Hypermotion | D168: CD Leganés | E168: Casa | F168: 1 x 1 | G168: 230134 | H168: 14 | I168: Sergio Molina | J168: MC | K168: 76 | L168: 0 | M168: 0 | N168: 6.7
A169: #11 | B169: 04/10/2025 | C169: LaLiga Hypermotion | D169: CD Leganés | E169: Casa | F169: 1 x 1 | G169: 85904 | H169: 30 | I169: Valle Gómez | J169: MC | K169: 76 | L169: 0 | M169: 0 | N169: 6.6
A170: #11 | B170: 04/10/2025 | C170: LaLiga Hypermotion | D170: CD Leganés | E170: Casa | F170: 1 x 1 | G170: 275520 | H170: 8 | I170: Manu Bueno | J170: MC | K170: 16 | L170: 0 | M170: N/D | N170: 6.1
A171: #11 | B171: 04/10/2025 | C171: LaLiga Hypermotion | D171: CD Leganés | E171: Casa | F171: 1 x 1 | G171: 266100 | H171: 6 | I171: Daniel Villahermosa | J171: MC | K171: 16 | L171: 0 | M171: N/D | N171: 6.1
A172: #11 | B172: 04/10/2025 | C172: LaLiga Hypermotion | D172: CD Leganés | E172: Casa | F172: 1 x 1 | G172: 75437 | H172: 29 | I172: Kim Min Su | J172: PE (SUB) | K172: 16 | L172: 0 | M172: N/D | N172: 6
A173: #11 | B173: 04/10/2025 | C173: LaLiga Hypermotion | D173: CD Leganés | E173: Casa | F173: 1 x 1 | G173: 279603 | H173: 15 | I173: Aingeru Olabarrieta | J173: PD (SUB) | K173: 16 | L173: 0 | M173: N/D | N173: 6
A174: #11 | B174: 04/10/2025 | C174: LaLiga Hypermotion | D174: CD Leganés | E174: Casa | F174: 1 x 1 | G174: 262498 | H174: 2 | I174: Álex Petxa | J174: LE | K174: 16 | L174: 0 | M174: N/D | N174: 5.9
A175: #12 | B175: 12/10/2025 | C175: LaLiga Hypermotion | D175: Real Sociedad B | E175: Fora | F175: 0 x 4 | G175: 236393 | H175: 22 | I175: Marc Cardona | J175: ATA | K175: 90 | L175: 4 | M175: 0 | N175: 10
A176: #12 | B176: 12/10/2025 | C176: LaLiga Hypermotion | D176: Real Sociedad B | E176: Fora | F176: 0 x 4 | G176: 278758 | H176: 16 | I176: Jastin | J176: PE | K176: 90 | L176: 0 | M176: N/D | N176: 7.4
A177: #12 | B177: 12/10/2025 | C177: LaLiga Hypermotion | D177: Real Sociedad B | E177: Fora | F177: 0 x 4 | G177: 271955 | H177: 5 | I177: Bomba | J177: ZAG | K177: 90 | L177: 0 | M177: 0 | N177: 7.2
A178: #12 | B178: 12/10/2025 | C178: LaLiga Hypermotion | D178: Real Sociedad B | E178: Fora | F178: 0 x 4 | G178: 276198 | H178: 25 | I178: Áron Yaakobishvili | J178: GOL | K178: 90 | L178: 0 | M178: 0 | N178: 7
A179: #12 | B179: 12/10/2025 | C179: LaLiga Hypermotion | D179: Real Sociedad B | E179: Fora | F179: 0 x 4 | G179: 247500 | H179: 12 | I179: Edgar González | J179: ZAG | K179: 90 | L179: 0 | M179: 0 | N179: 7
A180: #12 | B180: 12/10/2025 | C180: LaLiga Hypermotion | D180: Real Sociedad B | E180: Fora | F180: 0 x 4 | G180: 279881 | H180: 21 | I180: Efe Akman | J180: MC | K180: 90 | L180: 0 | M180: 2 | N180: 7
A181: #12 | B181: 12/10/2025 | C181: LaLiga Hypermotion | D181: Real Sociedad B | E181: Fora | F181: 0 x 4 | G181: 266100 | H181: 6 | I181: Daniel Villahermosa | J181: MC | K181: 83 | L181: 0 | M181: N/D | N181: 8.9
A182: #12 | B182: 12/10/2025 | C182: LaLiga Hypermotion | D182: Real Sociedad B | E182: Fora | F182: 0 x 4 | G182: 262498 | H182: 2 | I182: Álex Petxa | J182: LE | K182: 83 | L182: 0 | M182: N/D | N182: 7.8
A183: #12 | B183: 12/10/2025 | C183: LaLiga Hypermotion | D183: Real Sociedad B | E183: Fora | F183: 0 x 4 | G183: 275520 | H183: 8 | I183: Manu Bueno | J183: MC | K183: 83 | L183: 0 | M183: N/D | N183: 7
A184: #12 | B184: 12/10/2025 | C184: LaLiga Hypermotion | D184: Real Sociedad B | E184: Fora | F184: 0 x 4 | G184: 273022 | H184: 3 | I184: Yeray Cabanzón | J184: PD | K184: 83 | L184: 0 | M184: 4 | N184: 7
A185: #12 | B185: 12/10/2025 | C185: LaLiga Hypermotion | D185: Real Sociedad B | E185: Fora | F185: 0 x 4 | G185: 263006 | H185: 19 | I185: Imanol | J185: LD | K185: 83 | L185: 0 | M185: N/D | N185: 6.9
A186: #12 | B186: 12/10/2025 | C186: LaLiga Hypermotion | D186: Real Sociedad B | E186: Fora | F186: 0 x 4 | G186: 241505 | H186: 17 | I186: Thomas Carrique | J186: LD (SUB) | K186: 8 | L186: 0 | M186: N/D | N186: 6.6
A187: #12 | B187: 12/10/2025 | C187: LaLiga Hypermotion | D187: Real Sociedad B | E187: Fora | F187: 0 x 4 | G187: 230134 | H187: 14 | I187: Sergio Molina | J187: MC (SUB) | K187: 8 | L187: 0 | M187: 0 | N187: 6.5
A188: #12 | B188: 12/10/2025 | C188: LaLiga Hypermotion | D188: Real Sociedad B | E188: Fora | F188: 0 x 4 | G188: 279603 | H188: 15 | I188: Aingeru Olabarrieta | J188: PD (SUB) | K188: 8 | L188: 0 | M188: N/D | N188: 6.2
A189: #12 | B189: 12/10/2025 | C189: LaLiga Hypermotion | D189: Real Sociedad B | E189: Fora | F189: 0 x 4 | G189: 245704 | H189: 20 | I189: Martí Vilà | J189: LE (SUB) | K189: 8 | L189: 0 | M189: 0 | N189: 5.9
A190: #12 | B190: 12/10/2025 | C190: LaLiga Hypermotion | D190: Real Sociedad B | E190: Fora | F190: 0 x 4 | G190: 79752 | H190: 18 | I190: Marc Doménech | J190: MC (SUB) | K190: 8 | L190: 0 | M190: 0 | N190: 5.8
A191: #13 | B191: 19/10/2025 | C191: LaLiga Hypermotion | D191: Granada CF | E191: Casa | F191: 3 x 2 | G191: 230134 | H191: 14 | I191: Sergio Molina | J191: MC | K191: 90 | L191: 2 | M191: 0 | N191: 7.9
A192: #13 | B192: 19/10/2025 | C192: LaLiga Hypermotion | D192: Granada CF | E192: Casa | F192: 3 x 2 | G192: 79703 | H192: 4 | I192: Gaël Alonso | J192: ZAG | K192: 90 | L192: 0 | M192: 0 | N192: 7.2
A193: #13 | B193: 19/10/2025 | C193: LaLiga Hypermotion | D193: Granada CF | E193: Casa | F193: 3 x 2 | G193: 277311 | H193: 10 | I193: Álvaro Martín | J193: MC | K193: 90 | L193: 0 | M193: 0 | N193: 7.2
A194: #13 | B194: 19/10/2025 | C194: LaLiga Hypermotion | D194: Granada CF | E194: Casa | F194: 3 x 2 | G194: 228707 | H194: 23 | I194: Diego Alende | J194: ZAG | K194: 90 | L194: 0 | M194: 0 | N194: 6.5
A195: #13 | B195: 19/10/2025 | C195: LaLiga Hypermotion | D195: Granada CF | E195: Casa | F195: 3 x 2 | G195: 79752 | H195: 18 | I195: Marc Doménech | J195: MC | K195: 90 | L195: 0 | M195: 0 | N195: 6.4
A196: #13 | B196: 19/10/2025 | C196: LaLiga Hypermotion | D196: Granada CF | E196: Casa | F196: 3 x 2 | G196: 265405 | H196: 13 | I196: Jesús Owono | J196: GOL | K196: 90 | L196: 0 | M196: 0 | N196: 5.6
A197: #13 | B197: 19/10/2025 | C197: LaLiga Hypermotion | D197: Granada CF | E197: Casa | F197: 3 x 2 | G197: 279603 | H197: 15 | I197: Aingeru Olabarrieta | J197: PD | K197: 71 | L197: 0 | M197: N/D | N197: 8.7
...

Sheet Jogos e Adversários
A1: HISTÓRICO DE JOGOS DISPUTADOS — FC ANDORRA
A2: Campanha: 13J: 9V 4E 0D · 32 GP / 8 GC (Invicto!)
A4: Jogo | B4: Data | C4: Competição | D4: Etapa / Rodada | E4: Mando | F4: Mandante | G4: Placar | H4: Visitante | I4: Resultado | J4: Artilheiros Conciliados (stndgs) | K4: Goleiro Titular
A5: #1 | B5: 18/07/2025 | C5: Torneio de Pré-Temporada (Champions Trophy) | D5: Fase de Grupos - Rodada 1 | E5: Casa | F5: FC Andorra | G5: 1 x 1 | H5: Fortuna Sittard | I5: Empate | J5: Lautaro de León (1) | K5: Áron Yaakobishvili
A6: #2 | B6: 22/07/2025 | C6: Torneio de Pré-Temporada (Champions Trophy) | D6: Fase de Grupos - Rodada 2 | E6: Fora | F6: Aberdeen | G6: 0 x 2 | H6: FC Andorra | I6: Vitória | J6: Yeray Cabanzón (1), Imanol (1) | K6: Jesús Owono
A7: #3 | B7: 26/07/2025 | C7: Torneio de Pré-Temporada (Champions Trophy) | D7: Fase de Grupos - Rodada 3 (Título!) | E7: Casa | F7: FC Andorra | G7: 3 x 0 | H7: Estrela da Amadora | I7: Vitória | J7: Lautaro de León (2), Daniel Villahermosa (1) | K7: Áron Yaakobishvili
A8: #4 | B8: 17/08/2025 | C8: LaLiga Hypermotion | D8: Rodada 1 | E8: Fora | F8: UD Las Palmas | G8: 0 x 2 | H8: FC Andorra | I8: Vitória | J8: Kim Min Su (1), Marc Cardona (1) | K8: Áron Yaakobishvili
A9: #5 | B9: 23/08/2025 | C9: LaLiga Hypermotion | D9: Rodada 2 | E9: Fora | F9: Real Zaragoza | G9: 1 x 5 | H9: FC Andorra | I9: Vitória | J9: Yeray Cabanzón (2), Marc Cardona (3) | K9: Áron Yaakobishvili
A10: #6 | B10: 31/08/2025 | C10: LaLiga Hypermotion | D10: Rodada 3 | E10: Casa | F10: FC Andorra | G10: 1 x 1 | H10: Burgos CF | I10: Empate | J10: Manu Bueno (1) | K10: Jesús Owono
A11: #7 | B11: 07/09/2025 | C11: LaLiga Hypermotion | D11: Rodada 4 | E11: Casa | F11: FC Andorra | G11: 2 x 0 | H11: CD Mirandés | I11: Vitória | J11: Lautaro de León (1), Aingeru Olabarrieta (1) | K11: Jesús Owono
A12: #8 | B12: 13/09/2025 | C12: LaLiga Hypermotion | D12: Rodada 5 | E12: Casa | F12: FC Andorra | G12: 2 x 2 | H12: Córdoba CF | I12: Empate | J12: Marc Cardona (1), Manu Bueno (1) | K12: Áron Yaakobishvili
A13: #9 | B13: 21/09/2025 | C13: LaLiga Hypermotion | D13: Rodada 6 | E13: Fora | F13: SD Eibar | G13: 0 x 1 | H13: FC Andorra | I13: Vitória | J13: Lautaro de León (1) | K13: Áron Yaakobishvili
A14: #10 | B14: 27/09/2025 | C14: LaLiga Hypermotion | D14: Rodada 7 | E14: Fora | F14: Racing de Santander | G14: 0 x 5 | H14: FC Andorra | I14: Vitória | J14: Marc Cardona (4), Sergio Molina (1) | K14: Áron Yaakobishvili
A15: #11 | B15: 04/10/2025 | C15: LaLiga Hypermotion | D15: Rodada 11 | E15: Casa | F15: FC Andorra | G15: 1 x 1 | H15: CD Leganés | I15: Empate | J15: Marc Cardona (1) | K15: Jesús Owono
... A17: #13 | B17: 19/10/2025 | C17: LaLiga Hypermotion | D17: Rodada 13 | E17: Casa | F17: FC Andorra | G17: 3 x 2 | H17: Granada CF | I17: Vitória | J17: Sergio Molina (2), Marc Cardona (1) | K17: Jesús Owono

Sheet Classificação (Tabelas)
A1: TABELAS DE CLASSIFICAÇÃO — COMPETIÇÕES DE FC ANDORRA
A2: Dados Extraídos e Conciliados Diretamente do Bloco de Competições do Save (mlop)
A4: LaLiga Hypermotion (Espanha — Liga Nacional)
A5: Pos | B5: Clube | C5: Pontos | D5: Jogos | E5: Vitórias | F5: Empates | G5: Derrotas | H5: Gols Pró | I5: Gols Contra | J5: Saldo | K5: Casa / Fora
A6: 1º | B6: FC Andorra | C6: 24 | D6: 10 | E6: 7 | F6: 3 | G6: 0 | H6: 26 | I6: 7 | J6: 19 | K6: C: 2V 3E 0D (9:6) | F: 5V 0E 0D (17:1)
A7: 2º | B7: SD Eibar | C7: 23 | D7: 10 | E7: 7 | F7: 2 | G7: 1 | H7: 14 | I7: 6 | J7: 8 | K7: C: 3V 1E 1D (7:3) | F: 4V 1E 0D (7:3)
A8: 3º | B8: Real Sporting de Gijón | C8: 20 | D8: 10 | E8: 6 | F8: 2 | G8: 2 | H8: 20 | I8: 13 | J8: 7 | K8: C: 2V 2E 1D (7:8) | F: 4V 0E 1D (13:5)
A9: 4º | B9: Racing de Santander | C9: 20 | D9: 10 | E9: 6 | F9: 2 | G9: 2 | H9: 16 | I9: 14 | J9: 2 | K9: C: 4V 1E 1D (9:9) | F: 2V 1E 1D (7:5)
A10: 5º | B10: RC Deportivo | C10: 18 | D10: 10 | E10: 5 | F10: 3 | G10: 2 | H10: 16 | I10: 10 | J10: 6 | K10: C: 3V 0E 1D (8:5) | F: 2V 3E 1D (8:5)
A11: 6º | B11: Cádiz CF | C11: 17 | D11: 10 | E11: 5 | F11: 2 | G11: 3 | H11: 14 | I11: 7 | J11: 7 | K11: C: 4V 0E 2D (11:4) | F: 1V 2E 1D (3:3)
A12: 7º | B12: Albacete Balompié | C12: 17 | D12: 10 | E12: 5 | F12: 2 | G12: 3 | H12: 14 | I12: 8 | J12: 6 | K12: C: 2V 1E 1D (5:3) | F: 3V 1E 2D (9:5)
A13: 8º | B13: Real Valladolid | C13: 17 | D13: 10 | E13: 5 | F13: 2 | G13: 3 | H13: 9 | I13: 8 | J13: 1 | K13: C: 3V 1E 2D (4:4) | F: 2V 1E 1D (5:4)
A14: 9º | B14: Córdoba CF | C14: 16 | D14: 10 | E14: 4 | F14: 4 | G14: 2 | H14: 18 | I14: 12 | J14: 6 | K14: C: 2V 2E 1D (9:7) | F: 2V 2E 1D (9:5)
A15: 10º | B15: SD Huesca | C15: 15 | D15: 10 | E15: 3 | F15: 6 | G15: 1 | H15: 12 | I15: 10 | J15: 2 | K15: C: 1V 4E 0D (7:6) | F: 2V 2E 1D (5:4)
A16: 11º | B16: CD Leganés | C16: 14 | D16: 10 | E16: 3 | F16: 5 | G16: 2 | H16: 13 | I16: 11 | J16: 2 | K16: C: 1V 2E 2D (4:7) | F: 2V 3E 0D (9:4)
A17: 12º | B17: CD Castellón | C17: 14 | D17: 10 | E17: 4 | F17: 2 | G17: 4 | H17: 14 | I17: 15 | J17: -1 | K17: C: 2V 1E 2D (6:9) | F: 2V 1E 2D (8:6)
... A27: 22º | B27: Real Zaragoza | C27: 5 | D27: 9 | E27: 1 | F27: 2 | G27: 6 | H27: 10 | I27: 19 | J27: -9 | K27: C: 0V 0E 4D (2:11) | F: 1V 2E 2D (8:8)
A30: Torneio de Pré-Temporada (Champions Trophy) (Internacional — Pré-Temporada / Amistoso)
A31: Pos | B31: Clube | C31: Pontos | D31: Jogos | E31: Vitórias | F31: Empates | G31: Derrotas | H31: Gols Pró | I31: Gols Contra | J31: Saldo | K31: Casa / Fora
A32: 1º | B32: FC Andorra | C32: 7 | D32: 3 | E32: 2 | F32: 1 | G32: 0 | H32: 6 | I32: 1 | J32: 5 | K32: C: 1V 1E 0D (4:1) | F: 1V 0E 0D (2:0)
A33: 2º | B33: Cagliari | C33: 7 | D33: 3 | E33: 2 | F33: 1 | G33: 0 | H33: 6 | I33: 3 | J33: 3 | K33: C: 1V 1E 0D (4:2) | F: 1V 0E 0D (2:1)
A34: 3º | B34: AVS Futebol SAD | C34: 5 | D34: 3 | E34: 1 | F34: 2 | G34: 0 | H34: 3 | I34: 2 | J34: 1 | K34: C: 1V 1E 0D (3:2) | F: 0V 1E 0D (0:0)
A35: 4º | B35: Genoa | C35: 5 | D35: 3 | E35: 1 | F35: 2 | G35: 0 | H35: 3 | I35: 2 | J35: 1 | K35: C: 1V 0E 0D (1:0) | F: 0V 2E 0D (2:2)
A36: 5º | B36: Udinese | C36: 4 | D36: 3 | E36: 1 | F36: 1 | G36: 1 | H36: 3 | I36: 3 | J36: 0 | K36: C: 1V 0E 1D (2:2) | F: 0V 1E 0D (1:1)
A37: 6º | B37: Fortuna Sittard | C37: 2 | D37: 3 | E37: 0 | F37: 2 | G37: 1 | H37: 2 | I37: 5 | J37: -3 | K37: C: 0V 1E 0D (1:1) | F: 0V 1E 1D (1:4)
A38: 7º | B38: Estrela da Amadora | C38: 1 | D38: 3 | E38: 0 | F38: 1 | G38: 2 | H38: 1 | I38: 5 | J38: -4 | K38: C: 0V 1E 0D (0:0) | F: 0V 0E 2D (1:5)
A39: 8º | B39: Aberdeen | C39: 0 | D39: 3 | E39: 0 | F39: 0 | G39: 3 | H39: 2 | I39: 5 | J39: -3 | K39: C: 0V 0E 1D (1:2) | F: 0V 0E 2D (1:3)

Sheet Integridade dos Dados
A1: AUDITORIA AUTOMÁTICA DE INTEGRIDADE DOS DADOS (8 Verificados · 1 Parcial (N/D no Binário))
A2: Distingue rigorosamente métricas 100% verificadas por partida de métricas parciais (onde o jogo grava apenas o acumulado da competição)
A4: # | B4: Regra de Validação | C4: Status de Verificação | D4: Evidência Primária Encontrada no Save | E4: Critério Técnico de Auditoria
A5: 1 | B5: Conciliação Cruzada de Gols (Partidas × Logs Individuais × Elenco) | C5: =IF(SUM('Elenco Completo (Hub)'!$AB$5:$AB$29)=SUM('Desempenho por Jogo (Logs)'!$L$5:$L$206), "OK (VERIFICADO)", "DIVERGÊNCIA DETECTADA") -> OK (VERIFICADO) | D5: Partidas: 32 GP (26 Liga + 6 Pré-Temp) == Soma dos 90 Logs por Jogo: 32 Gols == Soma do Elenco: 32 Gols. | E5: Os gols acumulados no elenco são recalculados diretamente da soma dos logs por partida e conciliados com o placar de cada confronto.
A6: 2 | B6: Assistências e Participações em Gol (G+A): Competição vs. Logs por Partida | C6: PARCIAL (NÃO VERIFICADO POR PARTIDA) | D6: Fórmula G+A validada (32G + 30A = 62 G+A) e totais por competição validados no bloco stndgs (7 Liga + 5 Pré-Temp = 12 A). Nos 90 logs por partida: 65 atuações com assistência deduzida com certeza e 137 marcadas como 'N/D' (o binário do EA FC não grava assistências por partida nos slots históricos). | E6: Não aprova como 'OK' absoluto quando o jogo fornece apenas o acumulado da competição sem discriminar em qual rodada ocorreu cada assistência.
A7: 3 | B7: Fonte Única de Minutos e Jogos (Derivados 100% dos Logs por Partida) | C7: OK (VERIFICADO) | D7: 0 divergências entre soma dos logs e tabela do elenco. Teto de 13J (1170m): máximo registrado é Edgar González (930m). | E7: Garante que Jogos (T/R), Minutos e Nota Média do elenco sejam calculados exclusivamente a partir dos registros individuais por partida.
A8: 4 | B8: Percentuais de Passe/Drible e xG/xA sem Denominador Falso | C8: =IF(MAX('Elenco Completo (Hub)'!$Z$5:$Z$29)<=540, "OK (VERIFICADO)", "DIVERGÊNCIA DETECTADA") -> OK (VERIFICADO) | D8: Campos sem denominador acumulado no save (xG, xA, % passes e % dribles da temporada) exibidos como 'N/D' (nunca 0.00 ou 100% de jogo único). | E8: Impede que estatísticas de uma única partida (mxif) ou zeros sem tentativas registradas distorçam a análise da temporada.
A9: 5 | B9: Separação entre Margem de Potencial (POT − OVR) e Evolução Real | C9: OK (VERIFICADO) | D9: Margem POT (POT − OVR) validada em 25 atletas e separada da Evolução Real medida contra o baseline_snapshot.json. | E9: Distingue potencial restante de crescimento real obtido desde o início do acompanhamento do save.
A10: 6 | B10: Contratos Próximos do Fim (2026) e Multas sem Zero Ambíguo | C10: OK (VERIFICADO) | D10: Zero ambíguo eliminado ('Sem multa rescisória' / 'Emprestado'). Alertas de último ano (2026): 1 atletas sinalizados. | E10: Nunca trata ausência de multa como € 0 numérico e sinaliza vínculos que expiram ao término da temporada atual.
A11: 7 | B11: Conciliação Matemática das Tabelas de Classificação | C11: OK (VERIFICADO) | D11: Validadas 2 competições do clube: Pontos (V×3+E), Jogos (V+E+D) e Saldo (GP−GC) exatos em 100% dos clubes. | E11: Recalcula pontos, vitórias, empates, derrotas e saldo de gols e confere com os resultados registrados da equipe.
A12: 8 | B12: Trava de Amostra Mínima e Independência da Hierarquia Tática | C12: OK (VERIFICADO) | D12: 0 atletas com amostra curta (≤2J ou <150m) classificados como 'Amostra insuficiente — continuar observando' (0 recomendações precipitadas; hierarquia do treinador preservada). | E12: Exige ≥3 jogos e ≥150 minutos antes de sugerir maior rotação e jamais altera automaticamente o status de escalação definido pelo treinador.
A13: 9 | B13: Descrições 100% Derivadas dos Campos Numéricos (Zero Textos Manuais) | C13: =IF(SUM('Elenco Completo (Hub)'!$Z$5:$Z$29)=SUM('Desempenho por Jogo (Logs)'!$K$5:$K$206), "OK (VERIFICADO)", "DIVERGÊNCIA DETECTADA") -> OK (VERIFICADO) | D13: Todos os 25 textos descritivos gerados dinamicamente a partir de OVR, POT, Idade e Minutos atuais (0 contradições). | E13: Impede que descrições textuais antigas contradigam os valores numéricos atualizados.
